{
"meta":{"test_sets":[],"test_metrics":[],"learn_metrics":[{"best_value":"Min","name":"Logloss"}],"launch_mode":"Train","parameters":"","iteration_count":1000,"learn_sets":["learn"],"name":"experiment"},
"iterations":[
{"learn":[0.6639394904],"iteration":0,"passed_time":0.1616572504,"remaining_time":161.4955931},
{"learn":[0.6388215319],"iteration":1,"passed_time":0.1726048837,"remaining_time":86.12983695},
{"learn":[0.6132716763],"iteration":2,"passed_time":0.1794447505,"remaining_time":59.63547208},
{"learn":[0.5916786532],"iteration":3,"passed_time":0.1903149332,"remaining_time":47.38841836},
{"learn":[0.5713598261],"iteration":4,"passed_time":0.2026583124,"remaining_time":40.32900417},
{"learn":[0.5521128556],"iteration":5,"passed_time":0.2100394147,"remaining_time":34.79652971},
{"learn":[0.5338417874],"iteration":6,"passed_time":0.2204803639,"remaining_time":31.27671447},
{"learn":[0.5173157647],"iteration":7,"passed_time":0.2278609919,"remaining_time":28.254763},
{"learn":[0.5026575722],"iteration":8,"passed_time":0.2386396542,"remaining_time":26.27687748},
{"learn":[0.4886834562],"iteration":9,"passed_time":0.2495556629,"remaining_time":24.70601063},
{"learn":[0.4762175107],"iteration":10,"passed_time":0.2568852694,"remaining_time":23.09632104},
{"learn":[0.4644440594],"iteration":11,"passed_time":0.2678935842,"remaining_time":22.05657177},
{"learn":[0.4545357481],"iteration":12,"passed_time":0.274951147,"remaining_time":20.87513708},
{"learn":[0.4448381211],"iteration":13,"passed_time":0.2849673412,"remaining_time":20.06984274},
{"learn":[0.437207884],"iteration":14,"passed_time":0.2916987559,"remaining_time":19.15488497},
{"learn":[0.4303556266],"iteration":15,"passed_time":0.3023188683,"remaining_time":18.5926104},
{"learn":[0.4226493728],"iteration":16,"passed_time":0.3092365963,"remaining_time":17.88115142},
{"learn":[0.4152635012],"iteration":17,"passed_time":0.3216226959,"remaining_time":17.54630485},
{"learn":[0.4084674094],"iteration":18,"passed_time":0.3334632377,"remaining_time":17.21723348},
{"learn":[0.4021899916],"iteration":19,"passed_time":0.3408755107,"remaining_time":16.70290002},
{"learn":[0.3965372183],"iteration":20,"passed_time":0.3516042363,"remaining_time":16.39145464},
{"learn":[0.3912347351],"iteration":21,"passed_time":0.3583114595,"remaining_time":15.92857306},
{"learn":[0.3861205899],"iteration":22,"passed_time":0.3687633432,"remaining_time":15.66442549},
{"learn":[0.3821609969],"iteration":23,"passed_time":0.3776652988,"remaining_time":15.35838882},
{"learn":[0.3776558994],"iteration":24,"passed_time":0.3855287061,"remaining_time":15.03561954},
{"learn":[0.3735522322],"iteration":25,"passed_time":0.3994644913,"remaining_time":14.96455441},
{"learn":[0.3697142596],"iteration":26,"passed_time":0.4138197351,"remaining_time":14.91283712},
{"learn":[0.3659679755],"iteration":27,"passed_time":0.4222523113,"remaining_time":14.65818738},
{"learn":[0.3625399244],"iteration":28,"passed_time":0.4340146284,"remaining_time":14.53200704},
{"learn":[0.3590704431],"iteration":29,"passed_time":0.4463138655,"remaining_time":14.43081498},
{"learn":[0.3561098888],"iteration":30,"passed_time":0.4549018314,"remaining_time":14.21935079},
{"learn":[0.353981949],"iteration":31,"passed_time":0.4652782747,"remaining_time":14.07466781},
{"learn":[0.3508339301],"iteration":32,"passed_time":0.4728080612,"remaining_time":13.85470894},
{"learn":[0.3481219978],"iteration":33,"passed_time":0.4837014326,"remaining_time":13.74281129},
{"learn":[0.3455353969],"iteration":34,"passed_time":0.4951128738,"remaining_time":13.65096923},
{"learn":[0.3433776464],"iteration":35,"passed_time":0.5042209522,"remaining_time":13.50191661},
{"learn":[0.341128739],"iteration":36,"passed_time":0.5187060494,"remaining_time":13.50037637},
{"learn":[0.3392777924],"iteration":37,"passed_time":0.532072111,"remaining_time":13.46982555},
{"learn":[0.3375167227],"iteration":38,"passed_time":0.5426887834,"remaining_time":13.37240823},
{"learn":[0.335209722],"iteration":39,"passed_time":0.5511982408,"remaining_time":13.22875778},
{"learn":[0.3338797939],"iteration":40,"passed_time":0.5642100419,"remaining_time":13.19701049},
{"learn":[0.3320183326],"iteration":41,"passed_time":0.5745189902,"remaining_time":13.10450459},
{"learn":[0.3307691767],"iteration":42,"passed_time":0.5817340196,"remaining_time":12.94696411},
{"learn":[0.3290102776],"iteration":43,"passed_time":0.5919038879,"remaining_time":12.8604572},
{"learn":[0.3279830131],"iteration":44,"passed_time":0.6030739562,"remaining_time":12.79856952},
{"learn":[0.3268005598],"iteration":45,"passed_time":0.6109874907,"remaining_time":12.67134926},
{"learn":[0.3257057276],"iteration":46,"passed_time":0.6207494698,"remaining_time":12.58668606},
{"learn":[0.3243963659],"iteration":47,"passed_time":0.6290478944,"remaining_time":12.47611657},
{"learn":[0.3231559841],"iteration":48,"passed_time":0.6393879036,"remaining_time":12.40934482},
{"learn":[0.3220997332],"iteration":49,"passed_time":0.6474573888,"remaining_time":12.30169039},
{"learn":[0.3211131064],"iteration":50,"passed_time":0.6588521235,"remaining_time":12.25981696},
{"learn":[0.3195787763],"iteration":51,"passed_time":0.670743548,"remaining_time":12.22817084},
{"learn":[0.3184335183],"iteration":52,"passed_time":0.6798456269,"remaining_time":12.14743035},
{"learn":[0.3173569218],"iteration":53,"passed_time":0.6928479547,"remaining_time":12.13766973},
{"learn":[0.3161119266],"iteration":54,"passed_time":0.7062992495,"remaining_time":12.13550529},
{"learn":[0.3153326091],"iteration":55,"passed_time":0.7209171846,"remaining_time":12.15260397},
{"learn":[0.3144104137],"iteration":56,"passed_time":0.73301242,"remaining_time":12.1268546},
{"learn":[0.3132536324],"iteration":57,"passed_time":0.7431937155,"remaining_time":12.07049103},
{"learn":[0.312720891],"iteration":58,"passed_time":0.7560969533,"remaining_time":12.05910564},
{"learn":[0.3119536295],"iteration":59,"passed_time":0.7692411312,"remaining_time":12.05144439},
{"learn":[0.3111082332],"iteration":60,"passed_time":0.7779967506,"remaining_time":11.97604834},
{"learn":[0.3103994253],"iteration":61,"passed_time":0.7889963366,"remaining_time":11.93675103},
{"learn":[0.3098411566],"iteration":62,"passed_time":0.8000784503,"remaining_time":11.89957949},
{"learn":[0.3091523998],"iteration":63,"passed_time":0.8080800836,"remaining_time":11.81817122},
{"learn":[0.3084238469],"iteration":64,"passed_time":0.8212945147,"remaining_time":11.81400571},
{"learn":[0.307750389],"iteration":65,"passed_time":0.8330549304,"remaining_time":11.78898947},
{"learn":[0.3071833443],"iteration":66,"passed_time":0.8434172118,"remaining_time":11.74489938},
{"learn":[0.3064495778],"iteration":67,"passed_time":0.8550129167,"remaining_time":11.71870645},
{"learn":[0.3055552259],"iteration":68,"passed_time":0.864005737,"remaining_time":11.65781654},
{"learn":[0.3046420162],"iteration":69,"passed_time":0.8723531204,"remaining_time":11.58983431},
{"learn":[0.3037850886],"iteration":70,"passed_time":0.8829876781,"remaining_time":11.55345849},
{"learn":[0.3032770597],"iteration":71,"passed_time":0.8905555288,"remaining_time":11.47827126},
{"learn":[0.3023473489],"iteration":72,"passed_time":0.9013143568,"remaining_time":11.44545765},
{"learn":[0.3017864541],"iteration":73,"passed_time":0.9086134966,"remaining_time":11.36994727},
{"learn":[0.3012777085],"iteration":74,"passed_time":0.9191793283,"remaining_time":11.33654505},
{"learn":[0.3007547766],"iteration":75,"passed_time":0.9263575944,"remaining_time":11.26255812},
{"learn":[0.3001498195],"iteration":76,"passed_time":0.9373258026,"remaining_time":11.23573657},
{"learn":[0.299407876],"iteration":77,"passed_time":0.9479833823,"remaining_time":11.20564972},
{"learn":[0.2987376832],"iteration":78,"passed_time":0.955826677,"remaining_time":11.14324518},
{"learn":[0.29827258],"iteration":79,"passed_time":0.9668885318,"remaining_time":11.11921812},
{"learn":[0.2978628771],"iteration":80,"passed_time":0.9747336317,"remaining_time":11.05901491},
{"learn":[0.2973715336],"iteration":81,"passed_time":0.9854718406,"remaining_time":11.03247743},
{"learn":[0.2965600046],"iteration":82,"passed_time":0.9952422329,"remaining_time":10.99562804},
{"learn":[0.2961178495],"iteration":83,"passed_time":1.004052391,"remaining_time":10.94895227},
{"learn":[0.2956623147],"iteration":84,"passed_time":1.014302221,"remaining_time":10.91866509},
{"learn":[0.2950774891],"iteration":85,"passed_time":1.022140979,"remaining_time":10.86321924},
{"learn":[0.2946021716],"iteration":86,"passed_time":1.032543351,"remaining_time":10.83577103},
{"learn":[0.294239636],"iteration":87,"passed_time":1.040198587,"remaining_time":10.7802399},
{"learn":[0.2938082007],"iteration":88,"passed_time":1.051251062,"remaining_time":10.76055863},
{"learn":[0.2931076928],"iteration":89,"passed_time":1.05998057,"remaining_time":10.71758132},
{"learn":[0.2926025105],"iteration":90,"passed_time":1.070396404,"remaining_time":10.69220145},
{"learn":[0.292082216],"iteration":91,"passed_time":1.080886532,"remaining_time":10.66788012},
{"learn":[0.2915519631],"iteration":92,"passed_time":1.090677574,"remaining_time":10.63703828},
{"learn":[0.290931781],"iteration":93,"passed_time":1.101974715,"remaining_time":10.62116055},
{"learn":[0.2903802564],"iteration":94,"passed_time":1.116185305,"remaining_time":10.6331337},
{"learn":[0.2900542302],"iteration":95,"passed_time":1.138063127,"remaining_time":10.71676111},
{"learn":[0.2895846648],"iteration":96,"passed_time":1.158520036,"remaining_time":10.78498549},
{"learn":[0.2888940992],"iteration":97,"passed_time":1.168946679,"remaining_time":10.75908066},
{"learn":[0.288553628],"iteration":98,"passed_time":1.197138041,"remaining_time":10.89516541},
{"learn":[0.2881633473],"iteration":99,"passed_time":1.22592505,"remaining_time":11.03332545},
{"learn":[0.2876911583],"iteration":100,"passed_time":1.250351084,"remaining_time":11.12936261},
{"learn":[0.2874449136],"iteration":101,"passed_time":1.261686138,"remaining_time":11.1077858},
{"learn":[0.2869047053],"iteration":102,"passed_time":1.270169498,"remaining_time":11.0615732},
{"learn":[0.2865767801],"iteration":103,"passed_time":1.292286639,"remaining_time":11.13354643},
{"learn":[0.2861188476],"iteration":104,"passed_time":1.300610662,"remaining_time":11.08615755},
{"learn":[0.2855144355],"iteration":105,"passed_time":1.313335625,"remaining_time":11.0766231},
{"learn":[0.2849224172],"iteration":106,"passed_time":1.32038595,"remaining_time":11.01966966},
{"learn":[0.2846164014],"iteration":107,"passed_time":1.33144607,"remaining_time":10.99675828},
{"learn":[0.2843753259],"iteration":108,"passed_time":1.342887458,"remaining_time":10.97718096},
{"learn":[0.2839373033],"iteration":109,"passed_time":1.351933311,"remaining_time":10.93836951},
{"learn":[0.2835680301],"iteration":110,"passed_time":1.363192947,"remaining_time":10.91782459},
{"learn":[0.2830727531],"iteration":111,"passed_time":1.374541389,"remaining_time":10.89814958},
{"learn":[0.2827472877],"iteration":112,"passed_time":1.38227882,"remaining_time":10.85027711},
{"learn":[0.2824598598],"iteration":113,"passed_time":1.39311281,"remaining_time":10.827175},
{"learn":[0.2819745356],"iteration":114,"passed_time":1.400730796,"remaining_time":10.77953699},
{"learn":[0.2815319316],"iteration":115,"passed_time":1.411846415,"remaining_time":10.75924337},
{"learn":[0.2812923847],"iteration":116,"passed_time":1.419580356,"remaining_time":10.71358508},
{"learn":[0.2810351231],"iteration":117,"passed_time":1.430868135,"remaining_time":10.69513301},
{"learn":[0.2806796123],"iteration":118,"passed_time":1.444073334,"remaining_time":10.6909967},
{"learn":[0.2803628498],"iteration":119,"passed_time":1.454769489,"remaining_time":10.66830958},
{"learn":[0.2799763347],"iteration":120,"passed_time":1.46540092,"remaining_time":10.64535049},
{"learn":[0.2795955585],"iteration":121,"passed_time":1.478468823,"remaining_time":10.64012809},
{"learn":[0.2792157534],"iteration":122,"passed_time":1.490827789,"remaining_time":10.62972334},
{"learn":[0.2787781284],"iteration":123,"passed_time":1.500425998,"remaining_time":10.59978366},
{"learn":[0.2785253717],"iteration":124,"passed_time":1.513036363,"remaining_time":10.59125454},
{"learn":[0.2781104574],"iteration":125,"passed_time":1.524934426,"remaining_time":10.57771975},
{"learn":[0.277754879],"iteration":126,"passed_time":1.532408301,"remaining_time":10.53379879},
{"learn":[0.2773997026],"iteration":127,"passed_time":1.543924861,"remaining_time":10.51798811},
{"learn":[0.2771626298],"iteration":128,"passed_time":1.551109055,"remaining_time":10.47299215},
{"learn":[0.276529253],"iteration":129,"passed_time":1.561960026,"remaining_time":10.4531171},
{"learn":[0.2762513318],"iteration":130,"passed_time":1.572492735,"remaining_time":10.4312686},
{"learn":[0.2759565472],"iteration":131,"passed_time":1.579993967,"remaining_time":10.3896573},
{"learn":[0.2755808563],"iteration":132,"passed_time":1.592523543,"remaining_time":10.38133768},
{"learn":[0.2752834681],"iteration":133,"passed_time":1.599892234,"remaining_time":10.33960205},
{"learn":[0.2749568111],"iteration":134,"passed_time":1.609707054,"remaining_time":10.3140489},
{"learn":[0.274712457],"iteration":135,"passed_time":1.620411674,"remaining_time":10.29438005},
{"learn":[0.2743174598],"iteration":136,"passed_time":1.62891528,"remaining_time":10.26097728},
{"learn":[0.2738937967],"iteration":137,"passed_time":1.640398942,"remaining_time":10.24654992},
{"learn":[0.2735783612],"iteration":138,"passed_time":1.647959782,"remaining_time":10.20786598},
{"learn":[0.2733178709],"iteration":139,"passed_time":1.657737888,"remaining_time":10.18324702},
{"learn":[0.2729961005],"iteration":140,"passed_time":1.665724626,"remaining_time":10.1479252},
{"learn":[0.2726463877],"iteration":141,"passed_time":1.675610381,"remaining_time":10.12446272},
{"learn":[0.2717729594],"iteration":142,"passed_time":1.682487273,"remaining_time":10.083158},
{"learn":[0.2715081064],"iteration":143,"passed_time":1.692019125,"remaining_time":10.05811369},
{"learn":[0.27130781],"iteration":144,"passed_time":1.698538913,"remaining_time":10.01552256},
{"learn":[0.2710944831],"iteration":145,"passed_time":1.708374793,"remaining_time":9.992822421},
{"learn":[0.2707108177],"iteration":146,"passed_time":1.715365951,"remaining_time":9.953790178},
{"learn":[0.2704960448],"iteration":147,"passed_time":1.725130906,"remaining_time":9.931159002},
{"learn":[0.2702589746],"iteration":148,"passed_time":1.737266564,"remaining_time":9.922240579},
{"learn":[0.2699183381],"iteration":149,"passed_time":1.744824757,"remaining_time":9.88734029},
{"learn":[0.2696026642],"iteration":150,"passed_time":1.754940787,"remaining_time":9.86718363},
{"learn":[0.2694066736],"iteration":151,"passed_time":1.762183088,"remaining_time":9.831126703},
{"learn":[0.26916745],"iteration":152,"passed_time":1.773712695,"remaining_time":9.819180737},
{"learn":[0.2686753533],"iteration":153,"passed_time":1.787818221,"remaining_time":9.821391005},
{"learn":[0.2684098999],"iteration":154,"passed_time":1.803022587,"remaining_time":9.829381199},
{"learn":[0.2680987338],"iteration":155,"passed_time":1.81168135,"remaining_time":9.801660638},
{"learn":[0.2677795836],"iteration":156,"passed_time":1.823693239,"remaining_time":9.792187263},
{"learn":[0.2675050328],"iteration":157,"passed_time":1.836366874,"remaining_time":9.78620828},
{"learn":[0.2673669953],"iteration":158,"passed_time":1.845156935,"remaining_time":9.759603661},
{"learn":[0.2671853758],"iteration":159,"passed_time":1.856795927,"remaining_time":9.748178616},
{"learn":[0.2669170615],"iteration":160,"passed_time":1.868052247,"remaining_time":9.734756742},
{"learn":[0.26650602],"iteration":161,"passed_time":1.876767229,"remaining_time":9.708215664},
{"learn":[0.2661502718],"iteration":162,"passed_time":1.887709893,"remaining_time":9.693332393},
{"learn":[0.2658401518],"iteration":163,"passed_time":1.89506335,"remaining_time":9.660200978},
{"learn":[0.2655244429],"iteration":164,"passed_time":1.90643464,"remaining_time":9.647714694},
{"learn":[0.2652643602],"iteration":165,"passed_time":1.91892297,"remaining_time":9.64085396},
{"learn":[0.2650444259],"iteration":166,"passed_time":1.927678484,"remaining_time":9.61530645},
{"learn":[0.2648424548],"iteration":167,"passed_time":1.939610014,"remaining_time":9.605687688},
{"learn":[0.2644716935],"iteration":168,"passed_time":1.951339435,"remaining_time":9.595047753},
{"learn":[0.264129204],"iteration":169,"passed_time":1.959545225,"remaining_time":9.567191394},
{"learn":[0.2638566419],"iteration":170,"passed_time":1.971065261,"remaining_time":9.555632174},
{"learn":[0.263602513],"iteration":171,"passed_time":1.977436884,"remaining_time":9.519289187},
{"learn":[0.2631923145],"iteration":172,"passed_time":1.988980171,"remaining_time":9.508015038},
{"learn":[0.2629146334],"iteration":173,"passed_time":1.997539111,"remaining_time":9.48257072},
{"learn":[0.2627432578],"iteration":174,"passed_time":2.004713963,"remaining_time":9.450794399},
{"learn":[0.2624738209],"iteration":175,"passed_time":2.01050711,"remaining_time":9.412828744},
{"learn":[0.262238273],"iteration":176,"passed_time":2.02045,"remaining_time":9.394521753},
{"learn":[0.2617885895],"iteration":177,"passed_time":2.026087101,"remaining_time":9.356424702},
{"learn":[0.2615416238],"iteration":178,"passed_time":2.036105439,"remaining_time":9.33878528},
{"learn":[0.2613669933],"iteration":179,"passed_time":2.041789912,"remaining_time":9.301487377},
{"learn":[0.2609794453],"iteration":180,"passed_time":2.05194738,"remaining_time":9.284778477},
{"learn":[0.2606503023],"iteration":181,"passed_time":2.058389505,"remaining_time":9.25144294},
{"learn":[0.2602994444],"iteration":182,"passed_time":2.069010449,"remaining_time":9.237057576},
{"learn":[0.2600737409],"iteration":183,"passed_time":2.076080401,"remaining_time":9.206965256},
{"learn":[0.2597483367],"iteration":184,"passed_time":2.085608141,"remaining_time":9.187949379},
{"learn":[0.2595975053],"iteration":185,"passed_time":2.091478544,"remaining_time":9.153029759},
{"learn":[0.2592668266],"iteration":186,"passed_time":2.101832887,"remaining_time":9.137915171},
{"learn":[0.259013961],"iteration":187,"passed_time":2.10775426,"remaining_time":9.103704569},
{"learn":[0.2587203438],"iteration":188,"passed_time":2.117703906,"remaining_time":9.087078666},
{"learn":[0.2585065594],"iteration":189,"passed_time":2.124481946,"remaining_time":9.057001979},
{"learn":[0.2581882671],"iteration":190,"passed_time":2.134519313,"remaining_time":9.040974472},
{"learn":[0.2576799425],"iteration":191,"passed_time":2.140697781,"remaining_time":9.008769827},
{"learn":[0.2573821475],"iteration":192,"passed_time":2.150779932,"remaining_time":8.993157541},
{"learn":[0.2572486069],"iteration":193,"passed_time":2.157096757,"remaining_time":8.961958693},
{"learn":[0.2569576433],"iteration":194,"passed_time":2.167419136,"remaining_time":8.947550794},
{"learn":[0.2568080932],"iteration":195,"passed_time":2.173337784,"remaining_time":8.915120297},
{"learn":[0.2563621226],"iteration":196,"passed_time":2.18342,"remaining_time":8.899930256},
{"learn":[0.2561258236],"iteration":197,"passed_time":2.18953766,"remaining_time":8.868733352},
{"learn":[0.2559336216],"iteration":198,"passed_time":2.199716458,"remaining_time":8.85413509},
{"learn":[0.2557721668],"iteration":199,"passed_time":2.205963003,"remaining_time":8.823852011},
{"learn":[0.2555145251],"iteration":200,"passed_time":2.215943846,"remaining_time":8.808652405},
{"learn":[0.255192036],"iteration":201,"passed_time":2.222350201,"remaining_time":8.779383466},
{"learn":[0.254751292],"iteration":202,"passed_time":2.232530098,"remaining_time":8.765155115},
{"learn":[0.2543243517],"iteration":203,"passed_time":2.238556173,"remaining_time":8.7347584},
{"learn":[0.2540652521],"iteration":204,"passed_time":2.248415721,"remaining_time":8.719465843},
{"learn":[0.2538791281],"iteration":205,"passed_time":2.254661703,"remaining_time":8.690298022},
{"learn":[0.2535374928],"iteration":206,"passed_time":2.264684215,"remaining_time":8.67581924},
{"learn":[0.2532311106],"iteration":207,"passed_time":2.271095286,"remaining_time":8.647632051},
{"learn":[0.2530873013],"iteration":208,"passed_time":2.281195265,"remaining_time":8.633614617},
{"learn":[0.2528616436],"iteration":209,"passed_time":2.287482152,"remaining_time":8.60529},
{"learn":[0.252628138],"iteration":210,"passed_time":2.298107132,"remaining_time":8.593395864},
{"learn":[0.2524364589],"iteration":211,"passed_time":2.304365778,"remaining_time":8.565284119},
{"learn":[0.2522468123],"iteration":212,"passed_time":2.314632201,"remaining_time":8.552185644},
{"learn":[0.2521015239],"iteration":213,"passed_time":2.32069078,"remaining_time":8.52365866},
{"learn":[0.2520060585],"iteration":214,"passed_time":2.330788156,"remaining_time":8.510086988},
{"learn":[0.2517719926],"iteration":215,"passed_time":2.337047466,"remaining_time":8.482616729},
{"learn":[0.2516365209],"iteration":216,"passed_time":2.347532016,"remaining_time":8.470587874},
{"learn":[0.2514958528],"iteration":217,"passed_time":2.353991953,"remaining_time":8.444136271},
{"learn":[0.2511921133],"iteration":218,"passed_time":2.364038716,"remaining_time":8.430658617},
{"learn":[0.250843265],"iteration":219,"passed_time":2.370175829,"remaining_time":8.403350666},
{"learn":[0.2506113644],"iteration":220,"passed_time":2.381444654,"remaining_time":8.394323011},
{"learn":[0.2504541588],"iteration":221,"passed_time":2.387576585,"remaining_time":8.367272899},
{"learn":[0.2503158138],"iteration":222,"passed_time":2.3973522,"remaining_time":8.353106096},
{"learn":[0.2502114745],"iteration":223,"passed_time":2.403366764,"remaining_time":8.325949146},
{"learn":[0.2500131839],"iteration":224,"passed_time":2.414956794,"remaining_time":8.318184511},
{"learn":[0.2497695159],"iteration":225,"passed_time":2.425177812,"remaining_time":8.305697463},
{"learn":[0.2496505748],"iteration":226,"passed_time":2.433590649,"remaining_time":8.287073002},
{"learn":[0.249492004],"iteration":227,"passed_time":2.444873586,"remaining_time":8.278256177},
{"learn":[0.2493323576],"iteration":228,"passed_time":2.451901063,"remaining_time":8.255090479},
{"learn":[0.2492245853],"iteration":229,"passed_time":2.462561114,"remaining_time":8.244226338},
{"learn":[0.2488660476],"iteration":230,"passed_time":2.472035149,"remaining_time":8.229415711},
{"learn":[0.248620376],"iteration":231,"passed_time":2.480246594,"remaining_time":8.210471485},
{"learn":[0.2484541368],"iteration":232,"passed_time":2.490247916,"remaining_time":8.197511379},
{"learn":[0.2481394272],"iteration":233,"passed_time":2.498950062,"remaining_time":8.180323707},
{"learn":[0.247984524],"iteration":234,"passed_time":2.507991872,"remaining_time":8.164313965},
{"learn":[0.2478120845],"iteration":235,"passed_time":2.515226681,"remaining_time":8.142513493},
{"learn":[0.2475938626],"iteration":236,"passed_time":2.522813552,"remaining_time":8.121969368},
{"learn":[0.2473947549],"iteration":237,"passed_time":2.531538849,"remaining_time":8.105179005},
{"learn":[0.2472147334],"iteration":238,"passed_time":2.542760726,"remaining_time":8.096405492},
{"learn":[0.2470226837],"iteration":239,"passed_time":2.55024404,"remaining_time":8.075772793},
{"learn":[0.2468345969],"iteration":240,"passed_time":2.560464376,"remaining_time":8.063869135},
{"learn":[0.2466605993],"iteration":241,"passed_time":2.567580212,"remaining_time":8.042255376},
{"learn":[0.2465617406],"iteration":242,"passed_time":2.576785043,"remaining_time":8.027268631},
{"learn":[0.2463702094],"iteration":243,"passed_time":2.584830479,"remaining_time":8.008737057},
{"learn":[0.2460909501],"iteration":244,"passed_time":2.596226844,"remaining_time":8.000617419},
{"learn":[0.2458314629],"iteration":245,"passed_time":2.608422847,"remaining_time":7.99492206},
{"learn":[0.2456358188],"iteration":246,"passed_time":2.616154344,"remaining_time":7.975563648},
{"learn":[0.2454594445],"iteration":247,"passed_time":2.627965387,"remaining_time":7.968669237},
{"learn":[0.2453236083],"iteration":248,"passed_time":2.639588811,"remaining_time":7.961169467},
{"learn":[0.2450831349],"iteration":249,"passed_time":2.650445415,"remaining_time":7.951336246},
{"learn":[0.244905422],"iteration":250,"passed_time":2.662559655,"remaining_time":7.945247737},
{"learn":[0.2446585164],"iteration":251,"passed_time":2.676422599,"remaining_time":7.944302},
{"learn":[0.2444307112],"iteration":252,"passed_time":2.685525502,"remaining_time":7.929199802},
{"learn":[0.244214362],"iteration":253,"passed_time":2.695361304,"remaining_time":7.916297374},
{"learn":[0.2437866926],"iteration":254,"passed_time":2.708479577,"remaining_time":7.913008961},
{"learn":[0.2435217501],"iteration":255,"passed_time":2.71616899,"remaining_time":7.893866128},
{"learn":[0.2433025331],"iteration":256,"passed_time":2.729392405,"remaining_time":7.890811504},
{"learn":[0.2430295757],"iteration":257,"passed_time":2.743847682,"remaining_time":7.891220854},
{"learn":[0.2429143398],"iteration":258,"passed_time":2.757708879,"remaining_time":7.88981575},
{"learn":[0.242756202],"iteration":259,"passed_time":2.765483028,"remaining_time":7.870990157},
{"learn":[0.2425479804],"iteration":260,"passed_time":2.778658131,"remaining_time":7.867541604},
{"learn":[0.2424421129],"iteration":261,"passed_time":2.793721698,"remaining_time":7.869338218},
{"learn":[0.2422173499],"iteration":262,"passed_time":2.808154257,"remaining_time":7.869238355},
{"learn":[0.2420494968],"iteration":263,"passed_time":2.818116016,"remaining_time":7.856565863},
{"learn":[0.2419101192],"iteration":264,"passed_time":2.827739703,"remaining_time":7.842976158},
{"learn":[0.241666319],"iteration":265,"passed_time":2.841220708,"remaining_time":7.840060149},
{"learn":[0.2414151514],"iteration":266,"passed_time":2.85353677,"remaining_time":7.833866862},
{"learn":[0.2412314723],"iteration":267,"passed_time":2.86244522,"remaining_time":7.818320526},
{"learn":[0.2409349107],"iteration":268,"passed_time":2.874152501,"remaining_time":7.810429288},
{"learn":[0.240654558],"iteration":269,"passed_time":2.885941756,"remaining_time":7.802731415},
{"learn":[0.240470143],"iteration":270,"passed_time":2.894821367,"remaining_time":7.787176297},
{"learn":[0.2403206002],"iteration":271,"passed_time":2.906262708,"remaining_time":7.77852666},
{"learn":[0.2402060163],"iteration":272,"passed_time":2.914108461,"remaining_time":7.760281505},
{"learn":[0.2400216142],"iteration":273,"passed_time":2.925976052,"remaining_time":7.752768662},
{"learn":[0.2398133096],"iteration":274,"passed_time":2.938721336,"remaining_time":7.747538068},
{"learn":[0.2395350238],"iteration":275,"passed_time":2.947476065,"remaining_time":7.731785039},
{"learn":[0.2393111331],"iteration":276,"passed_time":2.957994473,"remaining_time":7.720685934},
{"learn":[0.2391020655],"iteration":277,"passed_time":2.971647055,"remaining_time":7.717730839},
{"learn":[0.2388955244],"iteration":278,"passed_time":2.98405334,"remaining_time":7.711478344},
{"learn":[0.2386681746],"iteration":279,"passed_time":2.991885745,"remaining_time":7.693420488},
{"learn":[0.2384874037],"iteration":280,"passed_time":3.004164813,"remaining_time":7.686813169},
{"learn":[0.2383507138],"iteration":281,"passed_time":3.015965318,"remaining_time":7.678947158},
{"learn":[0.2380737568],"iteration":282,"passed_time":3.024303159,"remaining_time":7.662280441},
{"learn":[0.237880116],"iteration":283,"passed_time":3.036896189,"remaining_time":7.656400251},
{"learn":[0.2376646911],"iteration":284,"passed_time":3.049105833,"remaining_time":7.649511126},
{"learn":[0.2374122472],"iteration":285,"passed_time":3.057533222,"remaining_time":7.633142379},
{"learn":[0.2371985145],"iteration":286,"passed_time":3.070119545,"remaining_time":7.627161101},
{"learn":[0.2369756297],"iteration":287,"passed_time":3.081785835,"remaining_time":7.618859426},
{"learn":[0.2368446338],"iteration":288,"passed_time":3.090505893,"remaining_time":7.603286125},
{"learn":[0.2366762116],"iteration":289,"passed_time":3.10338917,"remaining_time":7.597952795},
{"learn":[0.2365171087],"iteration":290,"passed_time":3.11629717,"remaining_time":7.592627813},
{"learn":[0.23634551],"iteration":291,"passed_time":3.124328488,"remaining_time":7.575426608},
{"learn":[0.2361743198],"iteration":292,"passed_time":3.136967155,"remaining_time":7.569405389},
{"learn":[0.2361001409],"iteration":293,"passed_time":3.149369322,"remaining_time":7.562771228},
{"learn":[0.235808586],"iteration":294,"passed_time":3.156997726,"remaining_time":7.544689481},
{"learn":[0.2357026425],"iteration":295,"passed_time":3.169428166,"remaining_time":7.538099422},
{"learn":[0.2354707008],"iteration":296,"passed_time":3.182181955,"remaining_time":7.532235401},
{"learn":[0.2352633431],"iteration":297,"passed_time":3.190677391,"remaining_time":7.516293719},
{"learn":[0.2351519476],"iteration":298,"passed_time":3.201867614,"remaining_time":7.506719723},
{"learn":[0.2348892641],"iteration":299,"passed_time":3.213814263,"remaining_time":7.498899946},
{"learn":[0.2346616755],"iteration":300,"passed_time":3.221357089,"remaining_time":7.480825931},
{"learn":[0.2344230006],"iteration":301,"passed_time":3.232181479,"remaining_time":7.4704062},
{"learn":[0.234233309],"iteration":302,"passed_time":3.239339635,"remaining_time":7.451550249},
{"learn":[0.2341065061],"iteration":303,"passed_time":3.266626399,"remaining_time":7.478855177},
{"learn":[0.2339921416],"iteration":304,"passed_time":3.276944975,"remaining_time":7.467136911},
{"learn":[0.2338379166],"iteration":305,"passed_time":3.283597038,"remaining_time":7.447112237},
{"learn":[0.2334715346],"iteration":306,"passed_time":3.291921865,"remaining_time":7.430950658},
{"learn":[0.2333644897],"iteration":307,"passed_time":3.299508844,"remaining_time":7.413182209},
{"learn":[0.2331566285],"iteration":308,"passed_time":3.307997392,"remaining_time":7.397495786},
{"learn":[0.2329903516],"iteration":309,"passed_time":3.314935576,"remaining_time":7.378404992},
{"learn":[0.2327347825],"iteration":310,"passed_time":3.321198442,"remaining_time":7.357896227},
{"learn":[0.2326094436],"iteration":311,"passed_time":3.331199583,"remaining_time":7.345722156},
{"learn":[0.2322670429],"iteration":312,"passed_time":3.338013068,"remaining_time":7.326565425},
{"learn":[0.2320540895],"iteration":313,"passed_time":3.347489407,"remaining_time":7.313304883},
{"learn":[0.2319472362],"iteration":314,"passed_time":3.354317401,"remaining_time":7.294309269},
{"learn":[0.2317629271],"iteration":315,"passed_time":3.364042095,"remaining_time":7.281660737},
{"learn":[0.2316066095],"iteration":316,"passed_time":3.370224275,"remaining_time":7.261398043},
{"learn":[0.2313831434],"iteration":317,"passed_time":3.378681426,"remaining_time":7.246102933},
{"learn":[0.231174133],"iteration":318,"passed_time":3.384930982,"remaining_time":7.226137926},
{"learn":[0.2310673275],"iteration":319,"passed_time":3.394162154,"remaining_time":7.212594577},
{"learn":[0.2307643363],"iteration":320,"passed_time":3.400826762,"remaining_time":7.193649133},
{"learn":[0.2306530225],"iteration":321,"passed_time":3.410767771,"remaining_time":7.181678724},
{"learn":[0.2304746259],"iteration":322,"passed_time":3.418811983,"remaining_time":7.16574524},
{"learn":[0.2302892644],"iteration":323,"passed_time":3.430187103,"remaining_time":7.156810128},
{"learn":[0.2301906201],"iteration":324,"passed_time":3.436419309,"remaining_time":7.137178565},
{"learn":[0.2300821759],"iteration":325,"passed_time":3.445788284,"remaining_time":7.124114428},
{"learn":[0.2298801418],"iteration":326,"passed_time":3.452297378,"remaining_time":7.105186957},
{"learn":[0.2296363617],"iteration":327,"passed_time":3.462576681,"remaining_time":7.094059543},
{"learn":[0.2294924728],"iteration":328,"passed_time":3.469051657,"remaining_time":7.075178304},
{"learn":[0.2292163427],"iteration":329,"passed_time":3.478769804,"remaining_time":7.062956875},
{"learn":[0.2290813309],"iteration":330,"passed_time":3.486097342,"remaining_time":7.045918796},
{"learn":[0.2288600315],"iteration":331,"passed_time":3.49472679,"remaining_time":7.031558723},
{"learn":[0.2284969069],"iteration":332,"passed_time":3.500895932,"remaining_time":7.012305064},
{"learn":[0.2283352678],"iteration":333,"passed_time":3.509606415,"remaining_time":6.998197222},
{"learn":[0.2280344162],"iteration":334,"passed_time":3.515959635,"remaining_time":6.979442261},
{"learn":[0.2277812885],"iteration":335,"passed_time":3.524674092,"remaining_time":6.965427373},
{"learn":[0.2276117785],"iteration":336,"passed_time":3.531016579,"remaining_time":6.946777423},
{"learn":[0.2274767324],"iteration":337,"passed_time":3.540118149,"remaining_time":6.933604185},
{"learn":[0.2271923707],"iteration":338,"passed_time":3.546668427,"remaining_time":6.915480325},
{"learn":[0.226912185],"iteration":339,"passed_time":3.554586946,"remaining_time":6.900080542},
{"learn":[0.2264698134],"iteration":340,"passed_time":3.5616808,"remaining_time":6.88313093},
{"learn":[0.2261434438],"iteration":341,"passed_time":3.568721488,"remaining_time":6.866136664},
{"learn":[0.2259299114],"iteration":342,"passed_time":3.575737221,"remaining_time":6.849152636},
{"learn":[0.2257075502],"iteration":343,"passed_time":3.582818137,"remaining_time":6.832350866},
{"learn":[0.2253464596],"iteration":344,"passed_time":3.591034348,"remaining_time":6.817760864},
{"learn":[0.2250450703],"iteration":345,"passed_time":3.597429052,"remaining_time":6.79976474},
{"learn":[0.2247984466],"iteration":346,"passed_time":3.604683129,"remaining_time":6.78345269},
{"learn":[0.2246100767],"iteration":347,"passed_time":3.610886387,"remaining_time":6.765223921},
{"learn":[0.2244860813],"iteration":348,"passed_time":3.616428148,"remaining_time":6.745830156},
{"learn":[0.2242696834],"iteration":349,"passed_time":3.62338175,"remaining_time":6.729137535},
{"learn":[0.224107006],"iteration":350,"passed_time":3.629153573,"remaining_time":6.710315297},
{"learn":[0.2238459412],"iteration":351,"passed_time":3.636363495,"remaining_time":6.694214615},
{"learn":[0.2237059801],"iteration":352,"passed_time":3.642692956,"remaining_time":6.676550546},
{"learn":[0.2235766452],"iteration":353,"passed_time":3.64842285,"remaining_time":6.657856388},
{"learn":[0.2233864349],"iteration":354,"passed_time":3.655326882,"remaining_time":6.64136856},
{"learn":[0.2232675892],"iteration":355,"passed_time":3.661421919,"remaining_time":6.623471112},
{"learn":[0.2231673792],"iteration":356,"passed_time":3.668826239,"remaining_time":6.60799796},
{"learn":[0.2230563327],"iteration":357,"passed_time":3.675476361,"remaining_time":6.591217385},
{"learn":[0.2228528008],"iteration":358,"passed_time":3.681121708,"remaining_time":6.572699205},
{"learn":[0.222633745],"iteration":359,"passed_time":3.688576307,"remaining_time":6.55746899},
{"learn":[0.222473112],"iteration":360,"passed_time":3.694420372,"remaining_time":6.539431074},
{"learn":[0.2223075228],"iteration":361,"passed_time":3.702304438,"remaining_time":6.525055888},
{"learn":[0.2222196542],"iteration":362,"passed_time":3.708062354,"remaining_time":6.506985453},
{"learn":[0.2219998607],"iteration":363,"passed_time":3.713530772,"remaining_time":6.488476843},
{"learn":[0.2217159168],"iteration":364,"passed_time":3.721763848,"remaining_time":6.474849434},
{"learn":[0.2213657702],"iteration":365,"passed_time":3.727543619,"remaining_time":6.457001788},
{"learn":[0.2212123373],"iteration":366,"passed_time":3.735685056,"remaining_time":6.443293299},
{"learn":[0.2210548558],"iteration":367,"passed_time":3.741478849,"remaining_time":6.425583241},
{"learn":[0.2209023844],"iteration":368,"passed_time":3.747395453,"remaining_time":6.40814778},
{"learn":[0.2207364536],"iteration":369,"passed_time":3.754710227,"remaining_time":6.393155251},
{"learn":[0.2205793935],"iteration":370,"passed_time":3.76030498,"remaining_time":6.375287958},
{"learn":[0.2203371399],"iteration":371,"passed_time":3.768652684,"remaining_time":6.362134101},
{"learn":[0.2202129262],"iteration":372,"passed_time":3.775067411,"remaining_time":6.345756748},
{"learn":[0.2199192525],"iteration":373,"passed_time":3.781406787,"remaining_time":6.329306548},
{"learn":[0.2196886815],"iteration":374,"passed_time":3.788503878,"remaining_time":6.314173131},
{"learn":[0.2194668305],"iteration":375,"passed_time":3.794619606,"remaining_time":6.297453814},
{"learn":[0.2193282754],"iteration":376,"passed_time":3.802291362,"remaining_time":6.283362118},
{"learn":[0.2191294427],"iteration":377,"passed_time":3.808570932,"remaining_time":6.267013543},
{"learn":[0.218986426],"iteration":378,"passed_time":3.81896734,"remaining_time":6.257463636},
{"learn":[0.2188048537],"iteration":379,"passed_time":3.826012865,"remaining_time":6.242442043},
{"learn":[0.2186782517],"iteration":380,"passed_time":3.833872775,"remaining_time":6.228785428},
{"learn":[0.2185739912],"iteration":381,"passed_time":3.83967545,"remaining_time":6.211830963},
{"learn":[0.2183754195],"iteration":382,"passed_time":3.845456409,"remaining_time":6.19489975},
{"learn":[0.218172976],"iteration":383,"passed_time":3.852643623,"remaining_time":6.180282479},
{"learn":[0.2179270775],"iteration":384,"passed_time":3.858834916,"remaining_time":6.164112918},
{"learn":[0.2178149148],"iteration":385,"passed_time":3.867614616,"remaining_time":6.152112368},
{"learn":[0.2176534896],"iteration":386,"passed_time":3.874092836,"remaining_time":6.136482967},
{"learn":[0.2175133451],"iteration":387,"passed_time":3.882312932,"remaining_time":6.123648234},
{"learn":[0.2173816361],"iteration":388,"passed_time":3.888433844,"remaining_time":6.107540048},
{"learn":[0.2170854481],"iteration":389,"passed_time":3.894188056,"remaining_time":6.090909523},
{"learn":[0.2169584065],"iteration":390,"passed_time":3.90139327,"remaining_time":6.076594632},
{"learn":[0.2168452823],"iteration":391,"passed_time":3.90712685,"remaining_time":6.060033481},
{"learn":[0.2166170752],"iteration":392,"passed_time":3.914110436,"remaining_time":6.045458104},
{"learn":[0.2163340251],"iteration":393,"passed_time":3.921141145,"remaining_time":6.030993741},
{"learn":[0.2162302528],"iteration":394,"passed_time":3.926953157,"remaining_time":6.014700405},
{"learn":[0.216105835],"iteration":395,"passed_time":3.933440962,"remaining_time":5.99949076},
{"learn":[0.2159364107],"iteration":396,"passed_time":3.939802061,"remaining_time":5.984132601},
{"learn":[0.2157870077],"iteration":397,"passed_time":3.947020314,"remaining_time":5.970116153},
{"learn":[0.2156583749],"iteration":398,"passed_time":3.954695405,"remaining_time":5.9568219},
{"learn":[0.2155355419],"iteration":399,"passed_time":3.964207126,"remaining_time":5.946310689},
{"learn":[0.2153720461],"iteration":400,"passed_time":3.973520463,"remaining_time":5.935508124},
{"learn":[0.2151911982],"iteration":401,"passed_time":3.983353124,"remaining_time":5.925485493},
{"learn":[0.2150156663],"iteration":402,"passed_time":3.992411686,"remaining_time":5.914317063},
{"learn":[0.2148018858],"iteration":403,"passed_time":4.002229038,"remaining_time":5.904278482},
{"learn":[0.2146535124],"iteration":404,"passed_time":4.011680357,"remaining_time":5.893703241},
{"learn":[0.2144348454],"iteration":405,"passed_time":4.019476803,"remaining_time":5.880712367},
{"learn":[0.2142302519],"iteration":406,"passed_time":4.029029095,"remaining_time":5.870305291},
{"learn":[0.2140707411],"iteration":407,"passed_time":4.03742858,"remaining_time":5.858229705},
{"learn":[0.2139395832],"iteration":408,"passed_time":4.047490195,"remaining_time":5.848573851},
{"learn":[0.2137485093],"iteration":409,"passed_time":4.055407974,"remaining_time":5.835830987},
{"learn":[0.2136254628],"iteration":410,"passed_time":4.064228941,"remaining_time":5.824405952},
{"learn":[0.2133782284],"iteration":411,"passed_time":4.07449719,"remaining_time":5.815059096},
{"learn":[0.2132039589],"iteration":412,"passed_time":4.084252244,"remaining_time":5.80497837},
{"learn":[0.2130401326],"iteration":413,"passed_time":4.092455721,"remaining_time":5.792703026},
{"learn":[0.2129244293],"iteration":414,"passed_time":4.100482536,"remaining_time":5.780198273},
{"learn":[0.212761037],"iteration":415,"passed_time":4.10862562,"remaining_time":5.767878275},
{"learn":[0.2126488349],"iteration":416,"passed_time":4.11447693,"remaining_time":5.752374221},
{"learn":[0.2125255934],"iteration":417,"passed_time":4.122075266,"remaining_time":5.739348816},
{"learn":[0.212394424],"iteration":418,"passed_time":4.128439443,"remaining_time":5.724637986},
{"learn":[0.2123030395],"iteration":419,"passed_time":4.134227904,"remaining_time":5.709171868},
{"learn":[0.2121020729],"iteration":420,"passed_time":4.140060856,"remaining_time":5.693812911},
{"learn":[0.2118276291],"iteration":421,"passed_time":4.147005727,"remaining_time":5.680022062},
{"learn":[0.211691895],"iteration":422,"passed_time":4.152725667,"remaining_time":5.664592694},
{"learn":[0.2115643604],"iteration":423,"passed_time":4.159645046,"remaining_time":5.650838553},
{"learn":[0.2110787372],"iteration":424,"passed_time":4.165894236,"remaining_time":5.636209848},
{"learn":[0.2108597232],"iteration":425,"passed_time":4.171580556,"remaining_time":5.620862064},
{"learn":[0.2106618665],"iteration":426,"passed_time":4.179177215,"remaining_time":5.608123054},
{"learn":[0.2103952972],"iteration":427,"passed_time":4.185103373,"remaining_time":5.593175536},
{"learn":[0.210226301],"iteration":428,"passed_time":4.192931569,"remaining_time":5.580801692},
{"learn":[0.2100203503],"iteration":429,"passed_time":4.198583465,"remaining_time":5.565564129},
{"learn":[0.2099067125],"iteration":430,"passed_time":4.204119806,"remaining_time":5.550218491},
{"learn":[0.209781759],"iteration":431,"passed_time":4.211057119,"remaining_time":5.536760286},
{"learn":[0.2096434603],"iteration":432,"passed_time":4.216642176,"remaining_time":5.521561464},
{"learn":[0.2095746406],"iteration":433,"passed_time":4.222570858,"remaining_time":5.506855082},
{"learn":[0.2094924996],"iteration":434,"passed_time":4.228454586,"remaining_time":5.492130669},
{"learn":[0.2093686091],"iteration":435,"passed_time":4.234095227,"remaining_time":5.477132358},
{"learn":[0.2092849997],"iteration":436,"passed_time":4.241801172,"remaining_time":5.464837665},
{"learn":[0.209146035],"iteration":437,"passed_time":4.247544128,"remaining_time":5.450045206},
{"learn":[0.2089786349],"iteration":438,"passed_time":4.253329395,"remaining_time":5.435348042},
{"learn":[0.2087765421],"iteration":439,"passed_time":4.261862097,"remaining_time":5.424188124},
{"learn":[0.2086427599],"iteration":440,"passed_time":4.269108651,"remaining_time":5.411409831},
{"learn":[0.2084317239],"iteration":441,"passed_time":4.278111096,"remaining_time":5.400873284},
{"learn":[0.2082363594],"iteration":442,"passed_time":4.286137466,"remaining_time":5.389116408},
{"learn":[0.2081230328],"iteration":443,"passed_time":4.294923661,"remaining_time":5.378327827},
{"learn":[0.2079796619],"iteration":444,"passed_time":4.302765769,"remaining_time":5.36637079},
{"learn":[0.2078517224],"iteration":445,"passed_time":4.312767301,"remaining_time":5.35711454},
{"learn":[0.2077301804],"iteration":446,"passed_time":4.32087605,"remaining_time":5.345513323},
{"learn":[0.2075987473],"iteration":447,"passed_time":4.328846623,"remaining_time":5.333757447},
{"learn":[0.2074569558],"iteration":448,"passed_time":4.337257986,"remaining_time":5.322559354},
{"learn":[0.2073241633],"iteration":449,"passed_time":4.344991816,"remaining_time":5.310545553},
{"learn":[0.2072292174],"iteration":450,"passed_time":4.352627426,"remaining_time":5.298431168},
{"learn":[0.2071098963],"iteration":451,"passed_time":4.360849956,"remaining_time":5.287048177},
{"learn":[0.2069955854],"iteration":452,"passed_time":4.36871406,"remaining_time":5.275246337},
{"learn":[0.2068967637],"iteration":453,"passed_time":4.377597744,"remaining_time":5.264688036},
{"learn":[0.2067632107],"iteration":454,"passed_time":4.388571946,"remaining_time":5.256641122},
{"learn":[0.2066408745],"iteration":455,"passed_time":4.402234979,"remaining_time":5.251789098},
{"learn":[0.2065388188],"iteration":456,"passed_time":4.411532716,"remaining_time":5.241711739},
{"learn":[0.2064564718],"iteration":457,"passed_time":4.418490224,"remaining_time":5.228868344},
{"learn":[0.2063299099],"iteration":458,"passed_time":4.427231527,"remaining_time":5.218153064},
{"learn":[0.2061274094],"iteration":459,"passed_time":4.434666287,"remaining_time":5.205912597},
{"learn":[0.2060113787],"iteration":460,"passed_time":4.44212713,"remaining_time":5.193723477},
{"learn":[0.2058992004],"iteration":461,"passed_time":4.448267808,"remaining_time":5.18001749},
{"learn":[0.205614684],"iteration":462,"passed_time":4.45521648,"remaining_time":5.167281316},
{"learn":[0.205366037],"iteration":463,"passed_time":4.461843024,"remaining_time":5.154197976},
{"learn":[0.2052541682],"iteration":464,"passed_time":4.468637439,"remaining_time":5.141335549},
{"learn":[0.205150773],"iteration":465,"passed_time":4.476297276,"remaining_time":5.12949087},
{"learn":[0.2050691469],"iteration":466,"passed_time":4.482275612,"remaining_time":5.11574497},
{"learn":[0.2049713999],"iteration":467,"passed_time":4.49018194,"remaining_time":5.104223915},
{"learn":[0.2048664021],"iteration":468,"passed_time":4.496925513,"remaining_time":5.091401807},
{"learn":[0.2047150214],"iteration":469,"passed_time":4.504695157,"remaining_time":5.079762624},
{"learn":[0.2044791046],"iteration":470,"passed_time":4.510740179,"remaining_time":5.066202876},
{"learn":[0.2043540684],"iteration":471,"passed_time":4.516911508,"remaining_time":5.052816263},
{"learn":[0.2042293333],"iteration":472,"passed_time":4.524453289,"remaining_time":5.040987068},
{"learn":[0.2041202987],"iteration":473,"passed_time":4.530342829,"remaining_time":5.027342464},
{"learn":[0.2039304102],"iteration":474,"passed_time":4.537486777,"remaining_time":5.015116964},
{"learn":[0.2038348433],"iteration":475,"passed_time":4.54343155,"remaining_time":5.001592715},
{"learn":[0.2036494334],"iteration":476,"passed_time":4.549559903,"remaining_time":4.988301529},
{"learn":[0.2034439186],"iteration":477,"passed_time":4.55704957,"remaining_time":4.976526937},
{"learn":[0.203172616],"iteration":478,"passed_time":4.562982257,"remaining_time":4.963076735},
{"learn":[0.203055852],"iteration":479,"passed_time":4.570014681,"remaining_time":4.950849238},
{"learn":[0.2029343928],"iteration":480,"passed_time":4.575797948,"remaining_time":4.937295499},
{"learn":[0.2028203888],"iteration":481,"passed_time":4.581549338,"remaining_time":4.923739745},
{"learn":[0.2026840085],"iteration":482,"passed_time":4.588307141,"remaining_time":4.911293565},
{"learn":[0.2024706506],"iteration":483,"passed_time":4.594193943,"remaining_time":4.897942303},
{"learn":[0.202340451],"iteration":484,"passed_time":4.600469972,"remaining_time":4.885035125},
{"learn":[0.2021787709],"iteration":485,"passed_time":4.607486482,"remaining_time":4.872938378},
{"learn":[0.2020653455],"iteration":486,"passed_time":4.613333859,"remaining_time":4.859630944},
{"learn":[0.2018843943],"iteration":487,"passed_time":4.620078714,"remaining_time":4.8472957},
{"learn":[0.2017770852],"iteration":488,"passed_time":4.625661037,"remaining_time":4.833768486},
{"learn":[0.2015855702],"iteration":489,"passed_time":4.631680513,"remaining_time":4.820728697},
{"learn":[0.2014078657],"iteration":490,"passed_time":4.637759637,"remaining_time":4.807779339},
{"learn":[0.2012725048],"iteration":491,"passed_time":4.64343556,"remaining_time":4.794441594},
{"learn":[0.2011641449],"iteration":492,"passed_time":4.649747469,"remaining_time":4.781788979},
{"learn":[0.2009894539],"iteration":493,"passed_time":4.655365757,"remaining_time":4.768451564},
{"learn":[0.2008837398],"iteration":494,"passed_time":4.661449983,"remaining_time":4.75562069},
{"learn":[0.2004915333],"iteration":495,"passed_time":4.668067553,"remaining_time":4.743358965},
{"learn":[0.2003942493],"iteration":496,"passed_time":4.673739506,"remaining_time":4.73016292},
{"learn":[0.200255557],"iteration":497,"passed_time":4.679683278,"remaining_time":4.717271095},
{"learn":[0.2001566564],"iteration":498,"passed_time":4.685991896,"remaining_time":4.704773427},
{"learn":[0.2000742191],"iteration":499,"passed_time":4.691781272,"remaining_time":4.691781272},
{"learn":[0.2000051391],"iteration":500,"passed_time":4.698060286,"remaining_time":4.679305554},
{"learn":[0.1998692956],"iteration":501,"passed_time":4.706600878,"remaining_time":4.669098082},
{"learn":[0.1997420649],"iteration":502,"passed_time":4.713857578,"remaining_time":4.657628661},
{"learn":[0.1995850475],"iteration":503,"passed_time":4.721179497,"remaining_time":4.646240139},
{"learn":[0.1994786997],"iteration":504,"passed_time":4.729128813,"remaining_time":4.635482698},
{"learn":[0.199246577],"iteration":505,"passed_time":4.73768589,"remaining_time":4.625329703},
{"learn":[0.1991635401],"iteration":506,"passed_time":4.744690003,"remaining_time":4.613672922},
{"learn":[0.1990581951],"iteration":507,"passed_time":4.752304316,"remaining_time":4.60262544},
{"learn":[0.198952146],"iteration":508,"passed_time":4.759282459,"remaining_time":4.590977775},
{"learn":[0.1988313292],"iteration":509,"passed_time":4.765985984,"remaining_time":4.579084573},
{"learn":[0.1987106769],"iteration":510,"passed_time":4.771988908,"remaining_time":4.566541244},
{"learn":[0.1985500772],"iteration":511,"passed_time":4.777773072,"remaining_time":4.553814959},
{"learn":[0.1983683185],"iteration":512,"passed_time":4.785021112,"remaining_time":4.542505422},
{"learn":[0.1982198194],"iteration":513,"passed_time":4.791448462,"remaining_time":4.530435705},
{"learn":[0.1980634672],"iteration":514,"passed_time":4.797434564,"remaining_time":4.517972356},
{"learn":[0.1978712594],"iteration":515,"passed_time":4.803293483,"remaining_time":4.505414818},
{"learn":[0.19778645],"iteration":516,"passed_time":4.809080638,"remaining_time":4.492816147},
{"learn":[0.1976500369],"iteration":517,"passed_time":4.816295685,"remaining_time":4.481572433},
{"learn":[0.1975395388],"iteration":518,"passed_time":4.822429505,"remaining_time":4.469342181},
{"learn":[0.1974228572],"iteration":519,"passed_time":4.828788465,"remaining_time":4.457343199},
{"learn":[0.1973252039],"iteration":520,"passed_time":4.835174901,"remaining_time":4.445391128},
{"learn":[0.1972265463],"iteration":521,"passed_time":4.841085189,"remaining_time":4.433024369},
{"learn":[0.197134006],"iteration":522,"passed_time":4.84772272,"remaining_time":4.421345579},
{"learn":[0.1970272178],"iteration":523,"passed_time":4.853692062,"remaining_time":4.409079049},
{"learn":[0.1968882623],"iteration":524,"passed_time":4.859735825,"remaining_time":4.396903841},
{"learn":[0.1967295891],"iteration":525,"passed_time":4.867236149,"remaining_time":4.386064515},
{"learn":[0.1965962519],"iteration":526,"passed_time":4.874348827,"remaining_time":4.374889934},
{"learn":[0.1964742596],"iteration":527,"passed_time":4.882021948,"remaining_time":4.364231741},
{"learn":[0.1963385208],"iteration":528,"passed_time":4.88938608,"remaining_time":4.353309723},
{"learn":[0.196190421],"iteration":529,"passed_time":4.897293804,"remaining_time":4.342883184},
{"learn":[0.1960650654],"iteration":530,"passed_time":4.904621941,"remaining_time":4.331954219},
{"learn":[0.1959544309],"iteration":531,"passed_time":4.915894035,"remaining_time":4.324508287},
{"learn":[0.1958705387],"iteration":532,"passed_time":4.923274961,"remaining_time":4.313638662},
{"learn":[0.1957325762],"iteration":533,"passed_time":4.933090171,"remaining_time":4.304906404},
{"learn":[0.1955940972],"iteration":534,"passed_time":4.939342802,"remaining_time":4.29307365},
{"learn":[0.1955049861],"iteration":535,"passed_time":4.948589604,"remaining_time":4.283853687},
{"learn":[0.1953675008],"iteration":536,"passed_time":4.955443065,"remaining_time":4.272570091},
{"learn":[0.1952431979],"iteration":537,"passed_time":4.96438848,"remaining_time":4.263099401},
{"learn":[0.1951417065],"iteration":538,"passed_time":4.971373845,"remaining_time":4.251954254},
{"learn":[0.1948560939],"iteration":539,"passed_time":4.978816208,"remaining_time":4.241213807},
{"learn":[0.1947400514],"iteration":540,"passed_time":4.985889812,"remaining_time":4.230172687},
{"learn":[0.1946414586],"iteration":541,"passed_time":4.992576645,"remaining_time":4.218819379},
{"learn":[0.1945270762],"iteration":542,"passed_time":4.999419128,"remaining_time":4.207614257},
{"learn":[0.1943962039],"iteration":543,"passed_time":5.006128777,"remaining_time":4.196313828},
{"learn":[0.194291414],"iteration":544,"passed_time":5.013661124,"remaining_time":4.185717085},
{"learn":[0.1941613068],"iteration":545,"passed_time":5.02060951,"remaining_time":4.174646003},
{"learn":[0.1939830644],"iteration":546,"passed_time":5.027538195,"remaining_time":4.163573679},
{"learn":[0.1938223429],"iteration":547,"passed_time":5.035520789,"remaining_time":4.15338576},
{"learn":[0.1936708515],"iteration":548,"passed_time":5.042302129,"remaining_time":4.142219053},
{"learn":[0.1935166653],"iteration":549,"passed_time":5.049140284,"remaining_time":4.131114778},
{"learn":[0.1934324776],"iteration":550,"passed_time":5.055502787,"remaining_time":4.119638387},
{"learn":[0.1932855233],"iteration":551,"passed_time":5.062979672,"remaining_time":4.109084951},
{"learn":[0.1932247629],"iteration":552,"passed_time":5.069574931,"remaining_time":4.097830008},
{"learn":[0.1931208525],"iteration":553,"passed_time":5.077165566,"remaining_time":4.087393218},
{"learn":[0.1930018908],"iteration":554,"passed_time":5.083925878,"remaining_time":4.076300929},
{"learn":[0.1928793583],"iteration":555,"passed_time":5.090813399,"remaining_time":4.065325808},
{"learn":[0.1927510423],"iteration":556,"passed_time":5.097468306,"remaining_time":4.054180358},
{"learn":[0.1926958096],"iteration":557,"passed_time":5.103793789,"remaining_time":4.042790062},
{"learn":[0.1926184188],"iteration":558,"passed_time":5.111035837,"remaining_time":4.032140974},
{"learn":[0.192535136],"iteration":559,"passed_time":5.117665509,"remaining_time":4.0210229},
{"learn":[0.1923512616],"iteration":560,"passed_time":5.124793935,"remaining_time":4.010311119},
{"learn":[0.1922084732],"iteration":561,"passed_time":5.132802135,"remaining_time":4.000297749},
{"learn":[0.1920470593],"iteration":562,"passed_time":5.141436394,"remaining_time":3.99077745},
{"learn":[0.1919076902],"iteration":563,"passed_time":5.148027601,"remaining_time":3.979680912},
{"learn":[0.1917532953],"iteration":564,"passed_time":5.154761857,"remaining_time":3.968710456},
{"learn":[0.1915701403],"iteration":565,"passed_time":5.162019131,"remaining_time":3.958156012},
{"learn":[0.1914153878],"iteration":566,"passed_time":5.168927113,"remaining_time":3.947346455},
{"learn":[0.1913114277],"iteration":567,"passed_time":5.176126747,"remaining_time":3.936772455},
{"learn":[0.1912164599],"iteration":568,"passed_time":5.183748785,"remaining_time":3.926530275},
{"learn":[0.1911380544],"iteration":569,"passed_time":5.190760071,"remaining_time":3.915836545},
{"learn":[0.1909657912],"iteration":570,"passed_time":5.197834025,"remaining_time":3.905202796},
{"learn":[0.1908777587],"iteration":571,"passed_time":5.204499539,"remaining_time":3.894275879},
{"learn":[0.1907240507],"iteration":572,"passed_time":5.211696429,"remaining_time":3.883759817},
{"learn":[0.1904543874],"iteration":573,"passed_time":5.218213554,"remaining_time":3.872750826},
{"learn":[0.1903255945],"iteration":574,"passed_time":5.225639754,"remaining_time":3.862429384},
{"learn":[0.1901519614],"iteration":575,"passed_time":5.23309367,"remaining_time":3.852138396},
{"learn":[0.1900727835],"iteration":576,"passed_time":5.240059066,"remaining_time":3.841499108},
{"learn":[0.1899379925],"iteration":577,"passed_time":5.248091571,"remaining_time":3.831651631},
{"learn":[0.1898343717],"iteration":578,"passed_time":5.254793245,"remaining_time":3.820842756},
{"learn":[0.1897484676],"iteration":579,"passed_time":5.262120514,"remaining_time":3.810501062},
{"learn":[0.189663452],"iteration":580,"passed_time":5.268754247,"remaining_time":3.799669586},
{"learn":[0.1895807404],"iteration":581,"passed_time":5.276137107,"remaining_time":3.789390568},
{"learn":[0.189461054],"iteration":582,"passed_time":5.282988152,"remaining_time":3.778741097},
{"learn":[0.1893445414],"iteration":583,"passed_time":5.290144042,"remaining_time":3.768321783},
{"learn":[0.1892651172],"iteration":584,"passed_time":5.29694862,"remaining_time":3.757664405},
{"learn":[0.1891395718],"iteration":585,"passed_time":5.303655554,"remaining_time":3.746951193},
{"learn":[0.1890703051],"iteration":586,"passed_time":5.310440535,"remaining_time":3.736306544},
{"learn":[0.1889508415],"iteration":587,"passed_time":5.316813414,"remaining_time":3.725386269},
{"learn":[0.1888204143],"iteration":588,"passed_time":5.32459275,"remaining_time":3.715462853},
{"learn":[0.1886721934],"iteration":589,"passed_time":5.331732245,"remaining_time":3.705102068},
{"learn":[0.1886233055],"iteration":590,"passed_time":5.33905872,"remaining_time":3.694881585},
{"learn":[0.1884556935],"iteration":591,"passed_time":5.345282666,"remaining_time":3.683911026},
{"learn":[0.1883360934],"iteration":592,"passed_time":5.350895007,"remaining_time":3.672536708},
{"learn":[0.1881922147],"iteration":593,"passed_time":5.358165082,"remaining_time":3.662314854},
{"learn":[0.1881057227],"iteration":594,"passed_time":5.364311948,"remaining_time":3.651338385},
{"learn":[0.1879706181],"iteration":595,"passed_time":5.37077658,"remaining_time":3.640593521},
{"learn":[0.1876393492],"iteration":596,"passed_time":5.376617473,"remaining_time":3.629441946},
{"learn":[0.1875401376],"iteration":597,"passed_time":5.382237973,"remaining_time":3.618159975},
{"learn":[0.1874262594],"iteration":598,"passed_time":5.389074793,"remaining_time":3.607711172},
{"learn":[0.1873340356],"iteration":599,"passed_time":5.394637981,"remaining_time":3.59642532},
{"learn":[0.1872492118],"iteration":600,"passed_time":5.400524763,"remaining_time":3.585373345},
{"learn":[0.1871513586],"iteration":601,"passed_time":5.407606844,"remaining_time":3.575128777},
{"learn":[0.1870338399],"iteration":602,"passed_time":5.41449714,"remaining_time":3.564768432},
{"learn":[0.1869381686],"iteration":603,"passed_time":5.421329317,"remaining_time":3.554381472},
{"learn":[0.1868009475],"iteration":604,"passed_time":5.427035633,"remaining_time":3.543271198},
{"learn":[0.1866912585],"iteration":605,"passed_time":5.433194377,"remaining_time":3.532472912},
{"learn":[0.1865956895],"iteration":606,"passed_time":5.439340942,"remaining_time":3.521682026},
{"learn":[0.1864632284],"iteration":607,"passed_time":5.444896232,"remaining_time":3.510525203},
{"learn":[0.1863125522],"iteration":608,"passed_time":5.451165167,"remaining_time":3.499844959},
{"learn":[0.1861795889],"iteration":609,"passed_time":5.459077176,"remaining_time":3.49022967},
{"learn":[0.1860678508],"iteration":610,"passed_time":5.4650042,"remaining_time":3.479356193},
{"learn":[0.1859829584],"iteration":611,"passed_time":5.471507823,"remaining_time":3.468864437},
{"learn":[0.1858721601],"iteration":612,"passed_time":5.477299041,"remaining_time":3.457935936},
{"learn":[0.185780818],"iteration":613,"passed_time":5.483127326,"remaining_time":3.447047472},
{"learn":[0.1856778016],"iteration":614,"passed_time":5.488809688,"remaining_time":3.436084114},
{"learn":[0.1854914662],"iteration":615,"passed_time":5.494600675,"remaining_time":3.425205616},
{"learn":[0.1853646904],"iteration":616,"passed_time":5.500595955,"remaining_time":3.414470423},
{"learn":[0.1852652021],"iteration":617,"passed_time":5.506305112,"remaining_time":3.40357371},
{"learn":[0.1851449944],"iteration":618,"passed_time":5.51213481,"remaining_time":3.392767953},
{"learn":[0.1850588406],"iteration":619,"passed_time":5.518526039,"remaining_time":3.382322411},
{"learn":[0.1849659136],"iteration":620,"passed_time":5.524322583,"remaining_time":3.371526987},
{"learn":[0.1847862713],"iteration":621,"passed_time":5.530045639,"remaining_time":3.360702977},
{"learn":[0.18470725],"iteration":622,"passed_time":5.536305025,"remaining_time":3.350219895},
{"learn":[0.1845578225],"iteration":623,"passed_time":5.542032971,"remaining_time":3.339430123},
{"learn":[0.1844242948],"iteration":624,"passed_time":5.547536497,"remaining_time":3.328521898},
{"learn":[0.1843343242],"iteration":625,"passed_time":5.553980181,"remaining_time":3.318192632},
{"learn":[0.1842583178],"iteration":626,"passed_time":5.559788159,"remaining_time":3.307497581},
{"learn":[0.1841608685],"iteration":627,"passed_time":5.565843391,"remaining_time":3.296964557},
{"learn":[0.1840073716],"iteration":628,"passed_time":5.57434021,"remaining_time":3.287885879},
{"learn":[0.1838621264],"iteration":629,"passed_time":5.580571811,"remaining_time":3.277478683},
{"learn":[0.1837759189],"iteration":630,"passed_time":5.586370502,"remaining_time":3.266831562},
{"learn":[0.1837213197],"iteration":631,"passed_time":5.592028556,"remaining_time":3.256117893},
{"learn":[0.1836278854],"iteration":632,"passed_time":5.598018661,"remaining_time":3.245612715},
{"learn":[0.1835266461],"iteration":633,"passed_time":5.604573479,"remaining_time":3.235447781},
{"learn":[0.1834322999],"iteration":634,"passed_time":5.610481074,"remaining_time":3.224922192},
{"learn":[0.1833620302],"iteration":635,"passed_time":5.616823456,"remaining_time":3.214659965},
{"learn":[0.1832581862],"iteration":636,"passed_time":5.622919686,"remaining_time":3.204269774},
{"learn":[0.1831850789],"iteration":637,"passed_time":5.628594392,"remaining_time":3.193653871},
{"learn":[0.1830837549],"iteration":638,"passed_time":5.635261865,"remaining_time":3.183614293},
{"learn":[0.1828948946],"iteration":639,"passed_time":5.641006373,"remaining_time":3.173066085},
{"learn":[0.1828083717],"iteration":640,"passed_time":5.646557685,"remaining_time":3.162424663},
{"learn":[0.1827011581],"iteration":641,"passed_time":5.653149744,"remaining_time":3.152379452},
{"learn":[0.182610303],"iteration":642,"passed_time":5.658804462,"remaining_time":3.141824561},
{"learn":[0.1825519194],"iteration":643,"passed_time":5.665019699,"remaining_time":3.131594741},
{"learn":[0.1824425298],"iteration":644,"passed_time":5.672383984,"remaining_time":3.12200979},
{"learn":[0.1823585904],"iteration":645,"passed_time":5.67829164,"remaining_time":3.111633499},
{"learn":[0.1822604509],"iteration":646,"passed_time":5.684746632,"remaining_time":3.101569646},
{"learn":[0.1821597502],"iteration":647,"passed_time":5.690445553,"remaining_time":3.091106226},
{"learn":[0.1820439993],"iteration":648,"passed_time":5.696459988,"remaining_time":3.080828129},
{"learn":[0.1819568069],"iteration":649,"passed_time":5.702658118,"remaining_time":3.070662064},
{"learn":[0.1818391048],"iteration":650,"passed_time":5.708449751,"remaining_time":3.060290266},
{"learn":[0.181766014],"iteration":651,"passed_time":5.715741549,"remaining_time":3.05073322},
{"learn":[0.1816917629],"iteration":652,"passed_time":5.721574219,"remaining_time":3.04040774},
{"learn":[0.1815713838],"iteration":653,"passed_time":5.727217672,"remaining_time":3.029995894},
{"learn":[0.181425306],"iteration":654,"passed_time":5.733761792,"remaining_time":3.020073005},
{"learn":[0.1813558357],"iteration":655,"passed_time":5.739744368,"remaining_time":3.009865949},
{"learn":[0.1812839755],"iteration":656,"passed_time":5.74592829,"remaining_time":2.99977687},
{"learn":[0.1811570609],"iteration":657,"passed_time":5.752083458,"remaining_time":2.989684715},
{"learn":[0.181078939],"iteration":658,"passed_time":5.758007309,"remaining_time":2.979484814},
{"learn":[0.1810086513],"iteration":659,"passed_time":5.764983369,"remaining_time":2.969839917},
{"learn":[0.180920086],"iteration":660,"passed_time":5.771680381,"remaining_time":2.960059983},
{"learn":[0.180791255],"iteration":661,"passed_time":5.777860588,"remaining_time":2.950025497},
{"learn":[0.180686106],"iteration":662,"passed_time":5.783495771,"remaining_time":2.939725603},
{"learn":[0.1806108467],"iteration":663,"passed_time":5.789547124,"remaining_time":2.929650352},
{"learn":[0.1804989985],"iteration":664,"passed_time":5.796051616,"remaining_time":2.919815476},
{"learn":[0.1802482171],"iteration":665,"passed_time":5.801740635,"remaining_time":2.90958164},
{"learn":[0.1801611094],"iteration":666,"passed_time":5.807816636,"remaining_time":2.899554632},
{"learn":[0.1800340983],"iteration":667,"passed_time":5.814410287,"remaining_time":2.88979673},
{"learn":[0.1799092701],"iteration":668,"passed_time":5.82014084,"remaining_time":2.879621253},
{"learn":[0.1798455917],"iteration":669,"passed_time":5.82609053,"remaining_time":2.869566977},
{"learn":[0.1797236185],"iteration":670,"passed_time":5.832256656,"remaining_time":2.859631058},
{"learn":[0.1796039651],"iteration":671,"passed_time":5.83809731,"remaining_time":2.849547497},
{"learn":[0.1794556747],"iteration":672,"passed_time":5.844239953,"remaining_time":2.839623276},
{"learn":[0.179346257],"iteration":673,"passed_time":5.850090703,"remaining_time":2.829569094},
{"learn":[0.1792593958],"iteration":674,"passed_time":5.855967772,"remaining_time":2.819540038},
{"learn":[0.1790814724],"iteration":675,"passed_time":5.862780475,"remaining_time":2.809971707},
{"learn":[0.179007906],"iteration":676,"passed_time":5.868673927,"remaining_time":2.799972937},
{"learn":[0.1789234355],"iteration":677,"passed_time":5.874304238,"remaining_time":2.789861305},
{"learn":[0.178845263],"iteration":678,"passed_time":5.881190049,"remaining_time":2.780356415},
{"learn":[0.1787815149],"iteration":679,"passed_time":5.887868798,"remaining_time":2.770761788},
{"learn":[0.1787091764],"iteration":680,"passed_time":5.894489325,"remaining_time":2.76114845},
{"learn":[0.1786025986],"iteration":681,"passed_time":5.900953893,"remaining_time":2.75147117},
{"learn":[0.1785161927],"iteration":682,"passed_time":5.907171077,"remaining_time":2.741688479},
{"learn":[0.1783558415],"iteration":683,"passed_time":5.913678913,"remaining_time":2.732050492},
{"learn":[0.1782375189],"iteration":684,"passed_time":5.919512524,"remaining_time":2.722111599},
{"learn":[0.1781442716],"iteration":685,"passed_time":5.925546448,"remaining_time":2.712276363},
{"learn":[0.1780525846],"iteration":686,"passed_time":5.931993522,"remaining_time":2.702640426},
{"learn":[0.1779830706],"iteration":687,"passed_time":5.937605383,"remaining_time":2.692634999},
{"learn":[0.1778661132],"iteration":688,"passed_time":5.944010924,"remaining_time":2.683000577},
{"learn":[0.1777588902],"iteration":689,"passed_time":5.950046381,"remaining_time":2.673209244},
{"learn":[0.1776549463],"iteration":690,"passed_time":5.955608146,"remaining_time":2.663216957},
{"learn":[0.1775849822],"iteration":691,"passed_time":5.963103908,"remaining_time":2.654098271},
{"learn":[0.177427274],"iteration":692,"passed_time":5.96986752,"remaining_time":2.644659926},
{"learn":[0.1773508412],"iteration":693,"passed_time":5.977194657,"remaining_time":2.63547776},
{"learn":[0.1772849805],"iteration":694,"passed_time":5.98388993,"remaining_time":2.626023638},
{"learn":[0.1771879993],"iteration":695,"passed_time":5.989588823,"remaining_time":2.616142244},
{"learn":[0.1771163743],"iteration":696,"passed_time":5.996139227,"remaining_time":2.606643021},
{"learn":[0.1770501625],"iteration":697,"passed_time":6.001753038,"remaining_time":2.596747017},
{"learn":[0.1769863792],"iteration":698,"passed_time":6.009306187,"remaining_time":2.587698372},
{"learn":[0.1768574783],"iteration":699,"passed_time":6.015084156,"remaining_time":2.57789321},
{"learn":[0.1767567917],"iteration":700,"passed_time":6.020804052,"remaining_time":2.568074767},
{"learn":[0.1766502405],"iteration":701,"passed_time":6.027168494,"remaining_time":2.558541611},
{"learn":[0.1765696439],"iteration":702,"passed_time":6.032851149,"remaining_time":2.548729433},
{"learn":[0.1764459423],"iteration":703,"passed_time":6.038701067,"remaining_time":2.538999312},
{"learn":[0.1763386838],"iteration":704,"passed_time":6.045043612,"remaining_time":2.529486334},
{"learn":[0.1762589628],"iteration":705,"passed_time":6.050597126,"remaining_time":2.519653761},
{"learn":[0.1761296817],"iteration":706,"passed_time":6.057516227,"remaining_time":2.510399229},
{"learn":[0.1760519069],"iteration":707,"passed_time":6.063096649,"remaining_time":2.500599183},
{"learn":[0.175979274],"iteration":708,"passed_time":6.069238625,"remaining_time":2.491041523},
{"learn":[0.1757790947],"iteration":709,"passed_time":6.075949902,"remaining_time":2.481726016},
{"learn":[0.1757166071],"iteration":710,"passed_time":6.083098346,"remaining_time":2.47259553},
{"learn":[0.1755511416],"iteration":711,"passed_time":6.089706309,"remaining_time":2.46325199},
{"learn":[0.1754727095],"iteration":712,"passed_time":6.095601007,"remaining_time":2.453629017},
{"learn":[0.1753210888],"iteration":713,"passed_time":6.103123243,"remaining_time":2.444668414},
{"learn":[0.175242698],"iteration":714,"passed_time":6.111948789,"remaining_time":2.436231336},
{"learn":[0.1751407606],"iteration":715,"passed_time":6.119813925,"remaining_time":2.427412227},
{"learn":[0.1750691293],"iteration":716,"passed_time":6.126953037,"remaining_time":2.418309218},
{"learn":[0.1749973262],"iteration":717,"passed_time":6.134832967,"remaining_time":2.409502642},
{"learn":[0.1749070633],"iteration":718,"passed_time":6.142706864,"remaining_time":2.400696285},
{"learn":[0.1748324533],"iteration":719,"passed_time":6.150363173,"remaining_time":2.3918079},
{"learn":[0.1747073427],"iteration":720,"passed_time":6.158381635,"remaining_time":2.383063074},
{"learn":[0.1745930606],"iteration":721,"passed_time":6.165175242,"remaining_time":2.373848639},
{"learn":[0.174515748],"iteration":722,"passed_time":6.172161151,"remaining_time":2.364714577},
{"learn":[0.174463957],"iteration":723,"passed_time":6.17928788,"remaining_time":2.355640131},
{"learn":[0.1743285262],"iteration":724,"passed_time":6.186374164,"remaining_time":2.346555717},
{"learn":[0.1742223121],"iteration":725,"passed_time":6.194877394,"remaining_time":2.338011578},
{"learn":[0.1741666676],"iteration":726,"passed_time":6.202239606,"remaining_time":2.329039082},
{"learn":[0.1740723588],"iteration":727,"passed_time":6.210141732,"remaining_time":2.320272735},
{"learn":[0.1739634526],"iteration":728,"passed_time":6.217143322,"remaining_time":2.311173992},
{"learn":[0.1738595241],"iteration":729,"passed_time":6.224695194,"remaining_time":2.302284524},
{"learn":[0.1737594623],"iteration":730,"passed_time":6.231325171,"remaining_time":2.293059468},
{"learn":[0.1736969774],"iteration":731,"passed_time":6.238193917,"remaining_time":2.28392892},
{"learn":[0.1736152151],"iteration":732,"passed_time":6.244089265,"remaining_time":2.274449978},
{"learn":[0.1735082337],"iteration":733,"passed_time":6.250804519,"remaining_time":2.265277932},
{"learn":[0.1734464369],"iteration":734,"passed_time":6.257635525,"remaining_time":2.256154305},
{"learn":[0.1733401219],"iteration":735,"passed_time":6.263543691,"remaining_time":2.246705889},
{"learn":[0.1732343969],"iteration":736,"passed_time":6.270136981,"remaining_time":2.237511569},
{"learn":[0.1731107829],"iteration":737,"passed_time":6.276094,"remaining_time":2.228098412},
{"learn":[0.1730054664],"iteration":738,"passed_time":6.282768985,"remaining_time":2.21894818},
{"learn":[0.1729410703],"iteration":739,"passed_time":6.289229812,"remaining_time":2.209729394},
{"learn":[0.1728740635],"iteration":740,"passed_time":6.2962403,"remaining_time":2.200710172},
{"learn":[0.1727890586],"iteration":741,"passed_time":6.302103122,"remaining_time":2.191297312},
{"learn":[0.1727226171],"iteration":742,"passed_time":6.308161413,"remaining_time":2.181961619},
{"learn":[0.1726339533],"iteration":743,"passed_time":6.314046761,"remaining_time":2.172575229},
{"learn":[0.1725769114],"iteration":744,"passed_time":6.320295232,"remaining_time":2.163322529},
{"learn":[0.1725032383],"iteration":745,"passed_time":6.326116033,"remaining_time":2.153932268},
{"learn":[0.1724151684],"iteration":746,"passed_time":6.331876755,"remaining_time":2.144531217},
{"learn":[0.1723114481],"iteration":747,"passed_time":6.338659153,"remaining_time":2.1354841},
{"learn":[0.1722594075],"iteration":748,"passed_time":6.34436722,"remaining_time":2.126083007},
{"learn":[0.1721858662],"iteration":749,"passed_time":6.350019172,"remaining_time":2.116673057},
{"learn":[0.1721180897],"iteration":750,"passed_time":6.356635216,"remaining_time":2.107592768},
{"learn":[0.1720508058],"iteration":751,"passed_time":6.363100854,"remaining_time":2.098469431},
{"learn":[0.1719606175],"iteration":752,"passed_time":6.368804096,"remaining_time":2.08910307},
{"learn":[0.1718961743],"iteration":753,"passed_time":6.374589634,"remaining_time":2.079773276},
{"learn":[0.1717759718],"iteration":754,"passed_time":6.380392286,"remaining_time":2.070458424},
{"learn":[0.1716934519],"iteration":755,"passed_time":6.38715353,"remaining_time":2.06146225},
{"learn":[0.1716220604],"iteration":756,"passed_time":6.392932365,"remaining_time":2.052156625},
{"learn":[0.1715508927],"iteration":757,"passed_time":6.398566121,"remaining_time":2.042813986},
{"learn":[0.1714226412],"iteration":758,"passed_time":6.406268366,"remaining_time":2.034137913},
{"learn":[0.1712975019],"iteration":759,"passed_time":6.412054563,"remaining_time":2.024859336},
{"learn":[0.1712222776],"iteration":760,"passed_time":6.418677169,"remaining_time":2.015852619},
{"learn":[0.1711458312],"iteration":761,"passed_time":6.424509458,"remaining_time":2.006605316},
{"learn":[0.1710342402],"iteration":762,"passed_time":6.430221243,"remaining_time":1.997329534},
{"learn":[0.1709705104],"iteration":763,"passed_time":6.436549423,"remaining_time":1.988253487},
{"learn":[0.1708620612],"iteration":764,"passed_time":6.442127434,"remaining_time":1.978954179},
{"learn":[0.1707401235],"iteration":765,"passed_time":6.448214251,"remaining_time":1.969820019},
{"learn":[0.1706775261],"iteration":766,"passed_time":6.4544057,"remaining_time":1.960725591},
{"learn":[0.170617055],"iteration":767,"passed_time":6.459886392,"remaining_time":1.951424014},
{"learn":[0.1705331734],"iteration":768,"passed_time":6.465888871,"remaining_time":1.942289115},
{"learn":[0.1704043761],"iteration":769,"passed_time":6.471816126,"remaining_time":1.933139882},
{"learn":[0.1703093164],"iteration":770,"passed_time":6.477556117,"remaining_time":1.923943386},
{"learn":[0.1702202803],"iteration":771,"passed_time":6.484163894,"remaining_time":1.915012134},
{"learn":[0.1701607842],"iteration":772,"passed_time":6.489830899,"remaining_time":1.905810626},
{"learn":[0.1700730915],"iteration":773,"passed_time":6.49619826,"remaining_time":1.896822748},
{"learn":[0.170002469],"iteration":774,"passed_time":6.503455764,"remaining_time":1.88810006},
{"learn":[0.1699322074],"iteration":775,"passed_time":6.509941608,"remaining_time":1.879158402},
{"learn":[0.16985147],"iteration":776,"passed_time":6.516363304,"remaining_time":1.870204655},
{"learn":[0.1697516532],"iteration":777,"passed_time":6.522218223,"remaining_time":1.861095688},
{"learn":[0.1696726739],"iteration":778,"passed_time":6.52806135,"remaining_time":1.851991731},
{"learn":[0.1695347999],"iteration":779,"passed_time":6.534565025,"remaining_time":1.843082443},
{"learn":[0.1694243738],"iteration":780,"passed_time":6.540606492,"remaining_time":1.834049708},
{"learn":[0.1693463912],"iteration":781,"passed_time":6.546613026,"remaining_time":1.825014884},
{"learn":[0.1692777799],"iteration":782,"passed_time":6.552980296,"remaining_time":1.816087771},
{"learn":[0.1692368805],"iteration":783,"passed_time":6.558789636,"remaining_time":1.807013471},
{"learn":[0.1691778387],"iteration":784,"passed_time":6.564513518,"remaining_time":1.797924085},
{"learn":[0.169111776],"iteration":785,"passed_time":6.570431751,"remaining_time":1.788896177},
{"learn":[0.1690233581],"iteration":786,"passed_time":6.576077556,"remaining_time":1.779802439},
{"learn":[0.1689477138],"iteration":787,"passed_time":6.582717025,"remaining_time":1.770984783},
{"learn":[0.1688452092],"iteration":788,"passed_time":6.588444002,"remaining_time":1.761928624},
{"learn":[0.1687836431],"iteration":789,"passed_time":6.594031538,"remaining_time":1.752843826},
{"learn":[0.168717738],"iteration":790,"passed_time":6.600790209,"remaining_time":1.744077312},
{"learn":[0.168613748],"iteration":791,"passed_time":6.606493916,"remaining_time":1.735038806},
{"learn":[0.1685368138],"iteration":792,"passed_time":6.612535978,"remaining_time":1.726097033},
{"learn":[0.1684445199],"iteration":793,"passed_time":6.620430628,"remaining_time":1.717643211},
{"learn":[0.1683619812],"iteration":794,"passed_time":6.626220639,"remaining_time":1.708648089},
{"learn":[0.1682738516],"iteration":795,"passed_time":6.633371318,"remaining_time":1.700009735},
{"learn":[0.1681771946],"iteration":796,"passed_time":6.639231982,"remaining_time":1.69104654},
{"learn":[0.1680746779],"iteration":797,"passed_time":6.64539518,"remaining_time":1.682167702},
{"learn":[0.167998039],"iteration":798,"passed_time":6.651485516,"remaining_time":1.673277333},
{"learn":[0.167907364],"iteration":799,"passed_time":6.657229058,"remaining_time":1.664307264},
{"learn":[0.1678303467],"iteration":800,"passed_time":6.663164944,"remaining_time":1.655393039},
{"learn":[0.1677402083],"iteration":801,"passed_time":6.668733852,"remaining_time":1.646395639},
{"learn":[0.1676729964],"iteration":802,"passed_time":6.674331419,"remaining_time":1.63741381},
{"learn":[0.1676082626],"iteration":803,"passed_time":6.681146509,"remaining_time":1.628737209},
{"learn":[0.1675240663],"iteration":804,"passed_time":6.686703786,"remaining_time":1.619760544},
{"learn":[0.167448201],"iteration":805,"passed_time":6.693153774,"remaining_time":1.611007236},
{"learn":[0.1673614969],"iteration":806,"passed_time":6.69957559,"remaining_time":1.602252898},
{"learn":[0.1673125849],"iteration":807,"passed_time":6.705252325,"remaining_time":1.593327285},
{"learn":[0.1671778215],"iteration":808,"passed_time":6.712001641,"remaining_time":1.584662934},
{"learn":[0.1671058196],"iteration":809,"passed_time":6.719273877,"remaining_time":1.576125971},
{"learn":[0.1669886183],"iteration":810,"passed_time":6.725204993,"remaining_time":1.567279585},
{"learn":[0.1668895871],"iteration":811,"passed_time":6.731778673,"remaining_time":1.558589151},
{"learn":[0.1668177087],"iteration":812,"passed_time":6.737497054,"remaining_time":1.549707194},
{"learn":[0.1667576512],"iteration":813,"passed_time":6.743445187,"remaining_time":1.540885509},
{"learn":[0.1666669885],"iteration":814,"passed_time":6.749764034,"remaining_time":1.532155026},
{"learn":[0.1666017154],"iteration":815,"passed_time":6.756754424,"remaining_time":1.52358188},
{"learn":[0.1665484056],"iteration":816,"passed_time":6.762578654,"remaining_time":1.5147514},
{"learn":[0.1664797188],"iteration":817,"passed_time":6.768389494,"remaining_time":1.505925291},
{"learn":[0.1662683706],"iteration":818,"passed_time":6.774175342,"remaining_time":1.497101022},
{"learn":[0.1662318027],"iteration":819,"passed_time":6.780847357,"remaining_time":1.488478688},
{"learn":[0.1661048345],"iteration":820,"passed_time":6.786747134,"remaining_time":1.479692737},
{"learn":[0.1660102251],"iteration":821,"passed_time":6.793134608,"remaining_time":1.471019416},
{"learn":[0.1659320226],"iteration":822,"passed_time":6.799030829,"remaining_time":1.462245998},
{"learn":[0.1658606951],"iteration":823,"passed_time":6.80467534,"remaining_time":1.453425801},
{"learn":[0.1657684139],"iteration":824,"passed_time":6.81101761,"remaining_time":1.444761311},
{"learn":[0.1657283498],"iteration":825,"passed_time":6.816972355,"remaining_time":1.436020811},
{"learn":[0.1656603721],"iteration":826,"passed_time":6.822612806,"remaining_time":1.4272213},
{"learn":[0.1655862792],"iteration":827,"passed_time":6.829474085,"remaining_time":1.418683023},
{"learn":[0.1655191396],"iteration":828,"passed_time":6.836442787,"remaining_time":1.410170949},
{"learn":[0.1654545545],"iteration":829,"passed_time":6.843141514,"remaining_time":1.401607298},
{"learn":[0.1653556773],"iteration":830,"passed_time":6.849081342,"remaining_time":1.392893799},
{"learn":[0.1652986884],"iteration":831,"passed_time":6.854638176,"remaining_time":1.384109632},
{"learn":[0.1652052272],"iteration":832,"passed_time":6.860489996,"remaining_time":1.375392352},
{"learn":[0.1651369221],"iteration":833,"passed_time":6.86630561,"remaining_time":1.366674738},
{"learn":[0.1650571773],"iteration":834,"passed_time":6.87204513,"remaining_time":1.357949038},
{"learn":[0.164958501],"iteration":835,"passed_time":6.878548176,"remaining_time":1.349380264},
{"learn":[0.1648967319],"iteration":836,"passed_time":6.884116643,"remaining_time":1.340634424},
{"learn":[0.1648039395],"iteration":837,"passed_time":6.89006888,"remaining_time":1.331970356},
{"learn":[0.1646759846],"iteration":838,"passed_time":6.897952876,"remaining_time":1.323683448},
{"learn":[0.1645891378],"iteration":839,"passed_time":6.903845859,"remaining_time":1.315018259},
{"learn":[0.1645101056],"iteration":840,"passed_time":6.910480933,"remaining_time":1.306499962},
{"learn":[0.1644302959],"iteration":841,"passed_time":6.916133098,"remaining_time":1.297801698},
{"learn":[0.1643590897],"iteration":842,"passed_time":6.921688402,"remaining_time":1.289092621},
{"learn":[0.1642695729],"iteration":843,"passed_time":6.929871706,"remaining_time":1.280876761},
{"learn":[0.1641497377],"iteration":844,"passed_time":6.935854459,"remaining_time":1.272257327},
{"learn":[0.1640563277],"iteration":845,"passed_time":6.942945681,"remaining_time":1.263845904},
{"learn":[0.1639968636],"iteration":846,"passed_time":6.948537887,"remaining_time":1.25516682},
{"learn":[0.1639272167],"iteration":847,"passed_time":6.954061783,"remaining_time":1.246482772},
{"learn":[0.1638093432],"iteration":848,"passed_time":6.960156819,"remaining_time":1.23790775},
{"learn":[0.1637027861],"iteration":849,"passed_time":6.96575481,"remaining_time":1.229250849},
{"learn":[0.1636193944],"iteration":850,"passed_time":6.97149013,"remaining_time":1.220625181},
{"learn":[0.1635299826],"iteration":851,"passed_time":6.977872289,"remaining_time":1.212118661},
{"learn":[0.1634700902],"iteration":852,"passed_time":6.983416665,"remaining_time":1.203472743},
{"learn":[0.1633190645],"iteration":853,"passed_time":6.990252692,"remaining_time":1.19505491},
{"learn":[0.1632348179],"iteration":854,"passed_time":6.995952474,"remaining_time":1.18644808},
{"learn":[0.1631798463],"iteration":855,"passed_time":7.001613504,"remaining_time":1.177841524},
{"learn":[0.1631235068],"iteration":856,"passed_time":7.008260568,"remaining_time":1.169406373},
{"learn":[0.1630509411],"iteration":857,"passed_time":7.014055448,"remaining_time":1.160834352},
{"learn":[0.1629975801],"iteration":858,"passed_time":7.020575362,"remaining_time":1.152387807},
{"learn":[0.1629318469],"iteration":859,"passed_time":7.028269556,"remaining_time":1.144136904},
{"learn":[0.1627868],"iteration":860,"passed_time":7.034275365,"remaining_time":1.135614722},
{"learn":[0.1627214435],"iteration":861,"passed_time":7.041360755,"remaining_time":1.127271211},
{"learn":[0.1626579863],"iteration":862,"passed_time":7.047147934,"remaining_time":1.118724527},
{"learn":[0.1625741515],"iteration":863,"passed_time":7.053011004,"remaining_time":1.110196177},
{"learn":[0.1623627282],"iteration":864,"passed_time":7.058879919,"remaining_time":1.101674901},
{"learn":[0.1622818102],"iteration":865,"passed_time":7.064577306,"remaining_time":1.093133209},
{"learn":[0.1622027288],"iteration":866,"passed_time":7.071019211,"remaining_time":1.08471229},
{"learn":[0.1620741076],"iteration":867,"passed_time":7.077375579,"remaining_time":1.076282922},
{"learn":[0.1619676406],"iteration":868,"passed_time":7.083289818,"remaining_time":1.067791676},
{"learn":[0.161852684],"iteration":869,"passed_time":7.090274929,"remaining_time":1.059466369},
{"learn":[0.1617785801],"iteration":870,"passed_time":7.095829704,"remaining_time":1.050932298},
{"learn":[0.16169881],"iteration":871,"passed_time":7.102576093,"remaining_time":1.042579977},
{"learn":[0.1616262198],"iteration":872,"passed_time":7.1084997,"remaining_time":1.03411164},
{"learn":[0.161485661],"iteration":873,"passed_time":7.115235994,"remaining_time":1.025766287},
{"learn":[0.1614081123],"iteration":874,"passed_time":7.122976481,"remaining_time":1.017568069},
{"learn":[0.1613164156],"iteration":875,"passed_time":7.129761486,"remaining_time":1.009235644},
{"learn":[0.1612199485],"iteration":876,"passed_time":7.13661321,"remaining_time":1.000916106},
{"learn":[0.1611372709],"iteration":877,"passed_time":7.145921206,"remaining_time":0.9929412154},
{"learn":[0.1610426451],"iteration":878,"passed_time":7.153277314,"remaining_time":0.9846946018},
{"learn":[0.1609823201],"iteration":879,"passed_time":7.159948813,"remaining_time":0.9763566564},
{"learn":[0.1608858844],"iteration":880,"passed_time":7.167457194,"remaining_time":0.9681355348},
{"learn":[0.1608413495],"iteration":881,"passed_time":7.175225616,"remaining_time":0.9599508194},
{"learn":[0.160742909],"iteration":882,"passed_time":7.18184242,"remaining_time":0.9516144542},
{"learn":[0.1606857962],"iteration":883,"passed_time":7.1897296,"remaining_time":0.9434486805},
{"learn":[0.1605818846],"iteration":884,"passed_time":7.196775247,"remaining_time":0.9351741847},
{"learn":[0.1605050984],"iteration":885,"passed_time":7.203900507,"remaining_time":0.9269127063},
{"learn":[0.1604293316],"iteration":886,"passed_time":7.210683431,"remaining_time":0.9186101778},
{"learn":[0.1603425612],"iteration":887,"passed_time":7.217508014,"remaining_time":0.9103163261},
{"learn":[0.1602608353],"iteration":888,"passed_time":7.225477473,"remaining_time":0.9021687283},
{"learn":[0.1601995648],"iteration":889,"passed_time":7.233118833,"remaining_time":0.8939809793},
{"learn":[0.1601302208],"iteration":890,"passed_time":7.243394257,"remaining_time":0.8861166936},
{"learn":[0.160071544],"iteration":891,"passed_time":7.25079997,"remaining_time":0.8778995479},
{"learn":[0.1600110995],"iteration":892,"passed_time":7.25819991,"remaining_time":0.8696835279},
{"learn":[0.1599327585],"iteration":893,"passed_time":7.26534195,"remaining_time":0.8614387547},
{"learn":[0.1598587358],"iteration":894,"passed_time":7.273632001,"remaining_time":0.8533311286},
{"learn":[0.159807712],"iteration":895,"passed_time":7.280916609,"remaining_time":0.8451063922},
{"learn":[0.1596623333],"iteration":896,"passed_time":7.290736483,"remaining_time":0.8371748693},
{"learn":[0.1596196785],"iteration":897,"passed_time":7.298149722,"remaining_time":0.8289657813},
{"learn":[0.1595699718],"iteration":898,"passed_time":7.307018382,"remaining_time":0.8209219762},
{"learn":[0.1595250936],"iteration":899,"passed_time":7.314637426,"remaining_time":0.8127374918},
{"learn":[0.1594608001],"iteration":900,"passed_time":7.323037605,"remaining_time":0.804640092},
{"learn":[0.1593324952],"iteration":901,"passed_time":7.33056023,"remaining_time":0.7964466769},
{"learn":[0.1592557431],"iteration":902,"passed_time":7.341062305,"remaining_time":0.7885747991},
{"learn":[0.1591511895],"iteration":903,"passed_time":7.348338138,"remaining_time":0.7803544925},
{"learn":[0.1590979294],"iteration":904,"passed_time":7.355035772,"remaining_time":0.7720755783},
{"learn":[0.1589972883],"iteration":905,"passed_time":7.36178985,"remaining_time":0.7638060109},
{"learn":[0.1589068977],"iteration":906,"passed_time":7.37020975,"remaining_time":0.7557105918},
{"learn":[0.1588240279],"iteration":907,"passed_time":7.37680717,"remaining_time":0.7474298014},
{"learn":[0.1587481251],"iteration":908,"passed_time":7.384385748,"remaining_time":0.7392509385},
{"learn":[0.1586708549],"iteration":909,"passed_time":7.391239869,"remaining_time":0.7310017453},
{"learn":[0.1586080214],"iteration":910,"passed_time":7.399029866,"remaining_time":0.7228470451},
{"learn":[0.1585426969],"iteration":911,"passed_time":7.405499547,"remaining_time":0.7145657457},
{"learn":[0.1584315835],"iteration":912,"passed_time":7.412617194,"remaining_time":0.7063501598},
{"learn":[0.158364678],"iteration":913,"passed_time":7.420285737,"remaining_time":0.6981888111},
{"learn":[0.1582657804],"iteration":914,"passed_time":7.426991688,"remaining_time":0.6899391185},
{"learn":[0.1581999262],"iteration":915,"passed_time":7.434487133,"remaining_time":0.6817651956},
{"learn":[0.1580146363],"iteration":916,"passed_time":7.442987022,"remaining_time":0.6736836672},
{"learn":[0.1579268935],"iteration":917,"passed_time":7.457488729,"remaining_time":0.6661373374},
{"learn":[0.1578531147],"iteration":918,"passed_time":7.469442265,"remaining_time":0.6583512769},
{"learn":[0.157791883],"iteration":919,"passed_time":7.479564944,"remaining_time":0.6503969516},
{"learn":[0.1577025406],"iteration":920,"passed_time":7.489025096,"remaining_time":0.6423810886},
{"learn":[0.157624067],"iteration":921,"passed_time":7.497970043,"remaining_time":0.6343185069},
{"learn":[0.1575116719],"iteration":922,"passed_time":7.506823625,"remaining_time":0.6262463912},
{"learn":[0.157391491],"iteration":923,"passed_time":7.51583139,"remaining_time":0.6181852659},
{"learn":[0.1572909554],"iteration":924,"passed_time":7.521876886,"remaining_time":0.6098819097},
{"learn":[0.1571579253],"iteration":925,"passed_time":7.527671866,"remaining_time":0.6015634104},
{"learn":[0.1571088964],"iteration":926,"passed_time":7.534380661,"remaining_time":0.5933223174},
{"learn":[0.1570545417],"iteration":927,"passed_time":7.5399136,"remaining_time":0.5849932965},
{"learn":[0.1569918795],"iteration":928,"passed_time":7.54584625,"remaining_time":0.5767008436},
{"learn":[0.1569212152],"iteration":929,"passed_time":7.552611273,"remaining_time":0.5684761173},
{"learn":[0.1568162812],"iteration":930,"passed_time":7.55860422,"remaining_time":0.5601973052},
{"learn":[0.1567280794],"iteration":931,"passed_time":7.565197607,"remaining_time":0.5519672074},
{"learn":[0.1566899534],"iteration":932,"passed_time":7.572565929,"remaining_time":0.5437962672},
{"learn":[0.1566229917],"iteration":933,"passed_time":7.578604493,"remaining_time":0.5355330798},
{"learn":[0.1565756192],"iteration":934,"passed_time":7.584983735,"remaining_time":0.5272983345},
{"learn":[0.1565140004],"iteration":935,"passed_time":7.590674807,"remaining_time":0.5190204996},
{"learn":[0.1564359356],"iteration":936,"passed_time":7.597256402,"remaining_time":0.5108080612},
{"learn":[0.1563759015],"iteration":937,"passed_time":7.60309308,"remaining_time":0.5025498624},
{"learn":[0.1563126923],"iteration":938,"passed_time":7.608848058,"remaining_time":0.4942915139},
{"learn":[0.1562283724],"iteration":939,"passed_time":7.61630262,"remaining_time":0.4861469757},
{"learn":[0.1561487898],"iteration":940,"passed_time":7.622140236,"remaining_time":0.4779025228},
{"learn":[0.1560873512],"iteration":941,"passed_time":7.628306864,"remaining_time":0.4696834375},
{"learn":[0.1559994336],"iteration":942,"passed_time":7.634465138,"remaining_time":0.4614682003},
{"learn":[0.155941296],"iteration":943,"passed_time":7.6401699,"remaining_time":0.4532304178},
{"learn":[0.1558739499],"iteration":944,"passed_time":7.646095109,"remaining_time":0.4450108264},
{"learn":[0.1558152374],"iteration":945,"passed_time":7.651740028,"remaining_time":0.4367800862},
{"learn":[0.1557319782],"iteration":946,"passed_time":7.657839908,"remaining_time":0.4285802694},
{"learn":[0.155639303],"iteration":947,"passed_time":7.665370355,"remaining_time":0.4204633528},
{"learn":[0.1555878885],"iteration":948,"passed_time":7.671756111,"remaining_time":0.4122861556},
{"learn":[0.1555425894],"iteration":949,"passed_time":7.678585403,"remaining_time":0.4041360738},
{"learn":[0.1554709588],"iteration":950,"passed_time":7.684132653,"remaining_time":0.3959227129},
{"learn":[0.1554077371],"iteration":951,"passed_time":7.69085224,"remaining_time":0.3877740625},
{"learn":[0.1553545029],"iteration":952,"passed_time":7.697119594,"remaining_time":0.379606108},
{"learn":[0.1552921128],"iteration":953,"passed_time":7.703008554,"remaining_time":0.3714238925},
{"learn":[0.1551851266],"iteration":954,"passed_time":7.708801905,"remaining_time":0.3632419746},
{"learn":[0.1551082444],"iteration":955,"passed_time":7.715265936,"remaining_time":0.3550959218},
{"learn":[0.1549987309],"iteration":956,"passed_time":7.721339933,"remaining_time":0.3469358591},
{"learn":[0.1549147866],"iteration":957,"passed_time":7.728080951,"remaining_time":0.3388093945},
{"learn":[0.1548571512],"iteration":958,"passed_time":7.733894244,"remaining_time":0.3306461564},
{"learn":[0.1547996197],"iteration":959,"passed_time":7.739503523,"remaining_time":0.3224793135},
{"learn":[0.1547469117],"iteration":960,"passed_time":7.745301333,"remaining_time":0.3143254443},
{"learn":[0.1546895542],"iteration":961,"passed_time":7.751012221,"remaining_time":0.3061730399},
{"learn":[0.154574446],"iteration":962,"passed_time":7.756718559,"remaining_time":0.2980255313},
{"learn":[0.1545155801],"iteration":963,"passed_time":7.763246701,"remaining_time":0.2899137772},
{"learn":[0.1544520813],"iteration":964,"passed_time":7.769219237,"remaining_time":0.2817851537},
{"learn":[0.1543809213],"iteration":965,"passed_time":7.775179181,"remaining_time":0.2736605509},
{"learn":[0.1543119738],"iteration":966,"passed_time":7.783483883,"remaining_time":0.2656204428},
{"learn":[0.1542219146],"iteration":967,"passed_time":7.789265197,"remaining_time":0.2574963701},
{"learn":[0.1541729247],"iteration":968,"passed_time":7.796042424,"remaining_time":0.249408994},
{"learn":[0.1540937126],"iteration":969,"passed_time":7.801657103,"remaining_time":0.241288364},
{"learn":[0.153988367],"iteration":970,"passed_time":7.80759223,"remaining_time":0.2331824662},
{"learn":[0.1539425518],"iteration":971,"passed_time":7.813654399,"remaining_time":0.2250846946},
{"learn":[0.1538627919],"iteration":972,"passed_time":7.819648063,"remaining_time":0.2169892063},
{"learn":[0.1537736956],"iteration":973,"passed_time":7.826378252,"remaining_time":0.2089176946},
{"learn":[0.1537419482],"iteration":974,"passed_time":7.831937942,"remaining_time":0.2008189216},
{"learn":[0.1536936218],"iteration":975,"passed_time":7.837505949,"remaining_time":0.1927255561},
{"learn":[0.1536194678],"iteration":976,"passed_time":7.843301251,"remaining_time":0.1846427111},
{"learn":[0.1535877714],"iteration":977,"passed_time":7.848884446,"remaining_time":0.1765597728},
{"learn":[0.1535150133],"iteration":978,"passed_time":7.854485286,"remaining_time":0.1684823197},
{"learn":[0.1534591088],"iteration":979,"passed_time":7.860887534,"remaining_time":0.1604262762},
{"learn":[0.1533875675],"iteration":980,"passed_time":7.866438624,"remaining_time":0.1523571191},
{"learn":[0.1533360194],"iteration":981,"passed_time":7.872750599,"remaining_time":0.1443070375},
{"learn":[0.1532747153],"iteration":982,"passed_time":7.880275831,"remaining_time":0.1362814742},
{"learn":[0.1531942646],"iteration":983,"passed_time":7.886022588,"remaining_time":0.1282280096},
{"learn":[0.153102761],"iteration":984,"passed_time":7.89313052,"remaining_time":0.1201999572},
{"learn":[0.1529947715],"iteration":985,"passed_time":7.89904702,"remaining_time":0.1121568542},
{"learn":[0.1529264305],"iteration":986,"passed_time":7.90521963,"remaining_time":0.1041214338},
{"learn":[0.1528605394],"iteration":987,"passed_time":7.911320665,"remaining_time":0.09608891496},
{"learn":[0.1527954755],"iteration":988,"passed_time":7.916960623,"remaining_time":0.08805517376},
{"learn":[0.1527446555],"iteration":989,"passed_time":7.923206547,"remaining_time":0.08003238936},
{"learn":[0.1526537329],"iteration":990,"passed_time":7.92900315,"remaining_time":0.07200911034},
{"learn":[0.1525725819],"iteration":991,"passed_time":7.934761876,"remaining_time":0.06399001513},
{"learn":[0.1525031976],"iteration":992,"passed_time":7.940563096,"remaining_time":0.05597577207},
{"learn":[0.1524523133],"iteration":993,"passed_time":7.946198191,"remaining_time":0.04796497902},
{"learn":[0.1523809054],"iteration":994,"passed_time":7.953373965,"remaining_time":0.03996670334},
{"learn":[0.1522593548],"iteration":995,"passed_time":7.959870234,"remaining_time":0.03196735034},
{"learn":[0.1520892204],"iteration":996,"passed_time":7.965893719,"remaining_time":0.02396958993},
{"learn":[0.1520084396],"iteration":997,"passed_time":7.972288923,"remaining_time":0.01597653091},
{"learn":[0.1519258595],"iteration":998,"passed_time":7.978103871,"remaining_time":0.00798608996},
{"learn":[0.1518159185],"iteration":999,"passed_time":7.984788594,"remaining_time":0}
]}